{"187f555524ffc032e08895d2f267ee01:3caf2ca4f91c42e8bd1a192af556e021":{"statistic":{"failed":1,"broken":0,"skipped":0,"passed":0,"unknown":0,"total":1},"items":[{"uid":"11b082ed72a71c99","reportUrl":"https://assurdly.github.io/northquest-automation-tests/86/67//#testresult/11b082ed72a71c99","status":"failed","statusDetails":"Test for valid error message","time":{"start":1744397280140,"stop":1744397280238,"duration":98}}]},"be49d53f8ba105c211cd357c8ead833f:4374228805f03c5eb601ea6a13ea4fad":{"statistic":{"failed":1,"broken":0,"skipped":0,"passed":0,"unknown":0,"total":1},"items":[{"uid":"325286149a607088","reportUrl":"https://assurdly.github.io/northquest-automation-tests/86/67//#testresult/325286149a607088","status":"failed","statusDetails":"Status code is 200","time":{"start":1744397271344,"stop":1744397271430,"duration":86}}]},"068327101040e9e925399f66ac781794:869a7bd747fb4b7670bca5a155d46293":{"statistic":{"failed":0,"broken":0,"skipped":0,"passed":1,"unknown":0,"total":1},"items":[{"uid":"52e90d18e70a4858","reportUrl":"https://assurdly.github.io/northquest-automation-tests/86/67//#testresult/52e90d18e70a4858","status":"passed","time":{"start":1744397280727,"stop":1744397280934,"duration":207}}]},"478dbf1c57f53858da6006d5e5345bc8:3dd6a7adc4472110b0a48ca2eae193da":{"statistic":{"failed":0,"broken":0,"skipped":0,"passed":1,"unknown":0,"total":1},"items":[{"uid":"20f6f9baa4accbdf","reportUrl":"https://assurdly.github.io/northquest-automation-tests/86/67//#testresult/20f6f9baa4accbdf","status":"passed","time":{"start":1744397269422,"stop":1744397269537,"duration":115}}]},"94144660b4a3dec0f93e4b6279011c8e:c3205f82884ea21de67e2e6b1f9a34ca":{"statistic":{"failed":1,"broken":0,"skipped":0,"passed":0,"unknown":0,"total":1},"items":[{"uid":"2fcb4595792637e9","reportUrl":"https://assurdly.github.io/northquest-automation-tests/86/67//#testresult/2fcb4595792637e9","status":"failed","statusDetails":"Status code is 400, Test for valid error message","time":{"start":1744397266406,"stop":1744397266477,"duration":71}}]},"1f94109c22d9e09a648445d339cfbae2:652c15db7d67579e6d4403e36305fa51":{"statistic":{"failed":0,"broken":0,"skipped":0,"passed":1,"unknown":0,"total":1},"items":[{"uid":"863b740c642fd595","reportUrl":"https://assurdly.github.io/northquest-automation-tests/86/67//#testresult/863b740c642fd595","status":"passed","time":{"start":1744397267436,"stop":1744397267530,"duration":94}}]},"a2bfdaaee78dfd176e22fe1ac3d28d70:9fe8641c248cca07537b010469fc7777":{"statistic":{"failed":0,"broken":0,"skipped":0,"passed":1,"unknown":0,"total":1},"items":[{"uid":"897bbbc38bdd2441","reportUrl":"https://assurdly.github.io/northquest-automation-tests/86/67//#testresult/897bbbc38bdd2441","status":"passed","time":{"start":1744397282390,"stop":1744397282530,"duration":140}}]},"67acc8c40cfa9fb0a58abd375abba573:8837d5e124aa2f36b9efe3d59c8e5a2a":{"statistic":{"failed":1,"broken":0,"skipped":0,"passed":0,"unknown":0,"total":1},"items":[{"uid":"2bf1aa8acbc26930","reportUrl":"https://assurdly.github.io/northquest-automation-tests/86/67//#testresult/2bf1aa8acbc26930","status":"failed","statusDetails":"Status code is 400, Test for valid error message","time":{"start":1744397278041,"stop":1744397278228,"duration":187}}]},"6ef244a215492a97d60e8ec6c272bd64:b9855ea962379312cb2697ea7cc793e7":{"statistic":{"failed":0,"broken":0,"skipped":0,"passed":1,"unknown":0,"total":1},"items":[{"uid":"d0c6fa5652384e42","reportUrl":"https://assurdly.github.io/northquest-automation-tests/86/67//#testresult/d0c6fa5652384e42","status":"passed","time":{"start":1744397264596,"stop":1744397264670,"duration":74}}]},"9195f4cce72ac6d27993016eba2201b1:ed2c2779c911c821b58b03549973316a":{"statistic":{"failed":1,"broken":0,"skipped":0,"passed":0,"unknown":0,"total":1},"items":[{"uid":"8a11555668ebe561","reportUrl":"https://assurdly.github.io/northquest-automation-tests/86/67//#testresult/8a11555668ebe561","status":"failed","statusDetails":"Status code is 400","time":{"start":1744397274735,"stop":1744397274807,"duration":72}}]},"b5bb255c37b24c736a69b171e1089366:5e731fec419d993dd0245aebe172d292":{"statistic":{"failed":1,"broken":0,"skipped":0,"passed":0,"unknown":0,"total":1},"items":[{"uid":"5cbfd6159610e3c2","reportUrl":"https://assurdly.github.io/northquest-automation-tests/86/67//#testresult/5cbfd6159610e3c2","status":"failed","statusDetails":"Successful POST request, Test for valid error message","time":{"start":1744397263310,"stop":1744397263405,"duration":95}}]},"ab4f762cc51eca3beea3fcc8a8e31134:ce314941ee7a9ac91702ebef390d0665":{"statistic":{"failed":0,"broken":0,"skipped":0,"passed":1,"unknown":0,"total":1},"items":[{"uid":"abbe6cb97882dcca","reportUrl":"https://assurdly.github.io/northquest-automation-tests/86/67//#testresult/abbe6cb97882dcca","status":"passed","time":{"start":1744397278827,"stop":1744397278931,"duration":104}}]},"3687fd2522f30beca0c570989b3a28ca:9d4b35a3bb59ebf71c9bb25469cfe435":{"statistic":{"failed":0,"broken":0,"skipped":0,"passed":1,"unknown":0,"total":1},"items":[{"uid":"2d859f09834d019b","reportUrl":"https://assurdly.github.io/northquest-automation-tests/86/67//#testresult/2d859f09834d019b","status":"passed","time":{"start":1744397264194,"stop":1744397264267,"duration":73}}]},"83b7fa3a4e76c5e857d3e02caa26b2fd:ba350198fc16cd364316c0c8668e56c8":{"statistic":{"failed":1,"broken":0,"skipped":0,"passed":0,"unknown":0,"total":1},"items":[{"uid":"c7f420ac1275b036","reportUrl":"https://assurdly.github.io/northquest-automation-tests/86/67//#testresult/c7f420ac1275b036","status":"failed","statusDetails":"Status code is 200, Test for valid status","time":{"start":1744397267892,"stop":1744397268033,"duration":141}}]},"20a968a60cf7c25100920bb735e42558:a5c9d35295e531543bb448b635accf89":{"statistic":{"failed":1,"broken":0,"skipped":0,"passed":0,"unknown":0,"total":1},"items":[{"uid":"9391a0c603c33979","reportUrl":"https://assurdly.github.io/northquest-automation-tests/86/67//#testresult/9391a0c603c33979","status":"failed","statusDetails":"Status code is 200","time":{"start":1744397271640,"stop":1744397271753,"duration":113}}]},"29a5f325529e6739f7cb464a7761d662:5079032bf07ff79105b4fef8ec176fed":{"statistic":{"failed":1,"broken":0,"skipped":0,"passed":0,"unknown":0,"total":1},"items":[{"uid":"556c86acc10756b5","reportUrl":"https://assurdly.github.io/northquest-automation-tests/86/67//#testresult/556c86acc10756b5","status":"failed","statusDetails":"Status code is 400, Test for valid error message","time":{"start":1744397268742,"stop":1744397268831,"duration":89}}]},"066af708968b6228cb0e5906a3dfad56:4bf34b2301b0cd92c7721755df5595dd":{"statistic":{"failed":0,"broken":0,"skipped":0,"passed":1,"unknown":0,"total":1},"items":[{"uid":"a6b577e650ab4d58","reportUrl":"https://assurdly.github.io/northquest-automation-tests/86/67//#testresult/a6b577e650ab4d58","status":"passed","time":{"start":1744397282744,"stop":1744397282826,"duration":82}}]},"d6ff6051d56603882ccfe55d550226c9:6b214820c9d474dd3c1ce54b7905c921":{"statistic":{"failed":1,"broken":0,"skipped":0,"passed":0,"unknown":0,"total":1},"items":[{"uid":"c9fc92e73348aa8d","reportUrl":"https://assurdly.github.io/northquest-automation-tests/86/67//#testresult/c9fc92e73348aa8d","status":"failed","statusDetails":"Status code is 400, Test for valid error message","time":{"start":1744397266864,"stop":1744397266936,"duration":72}}]},"c3baca87fdb89e18a0fb393e5f53e052:046e937abb6822d42e98a9d58378ae00":{"statistic":{"failed":0,"broken":0,"skipped":0,"passed":1,"unknown":0,"total":1},"items":[{"uid":"837a3ca3452c81f3","reportUrl":"https://assurdly.github.io/northquest-automation-tests/86/67//#testresult/837a3ca3452c81f3","status":"passed","time":{"start":1744397284557,"stop":1744397284747,"duration":190}}]},"c60e46742c4c42c841943fd54aca3ce9:022af40f8bae7ac6be9f5cbb3d498c77":{"statistic":{"failed":0,"broken":0,"skipped":0,"passed":1,"unknown":0,"total":1},"items":[{"uid":"61de9ee60587fb1","reportUrl":"https://assurdly.github.io/northquest-automation-tests/86/67//#testresult/61de9ee60587fb1","status":"passed","time":{"start":1744397263892,"stop":1744397263965,"duration":73}}]},"e4da20088ee250c4828aace2c0bec96c:8922374510b903db3b9a7bdecec7aa6a":{"statistic":{"failed":1,"broken":0,"skipped":0,"passed":0,"unknown":0,"total":1},"items":[{"uid":"4700b58fd638e18d","reportUrl":"https://assurdly.github.io/northquest-automation-tests/86/67//#testresult/4700b58fd638e18d","status":"failed","statusDetails":"Status code is 200","time":{"start":1744397271839,"stop":1744397271942,"duration":103}}]},"d92dde1a524ad9861fc47e9c9f2a12a0:a0bfa8d4c548b1464afcd5d89227c578":{"statistic":{"failed":1,"broken":0,"skipped":0,"passed":0,"unknown":0,"total":1},"items":[{"uid":"e2c382a9f91be975","reportUrl":"https://assurdly.github.io/northquest-automation-tests/86/67//#testresult/e2c382a9f91be975","status":"failed","statusDetails":"Status code is 200 or 202, Valid status in response","time":{"start":1744397273739,"stop":1744397273837,"duration":98}}]},"87e03f7b29e02a2b9a82dec3015bbdd6:bd0e4d07b2ad626d41af52df683be5e9":{"statistic":{"failed":1,"broken":0,"skipped":0,"passed":0,"unknown":0,"total":1},"items":[{"uid":"a7102b75c9a4c92f","reportUrl":"https://assurdly.github.io/northquest-automation-tests/86/67//#testresult/a7102b75c9a4c92f","status":"failed","statusDetails":"Status code is 400","time":{"start":1744397274532,"stop":1744397274629,"duration":97}}]},"f68e42d3d636e650dcea94fd2c45642b:8fb72cc66cd0fb364c4f21195159c921":{"statistic":{"failed":0,"broken":0,"skipped":0,"passed":1,"unknown":0,"total":1},"items":[{"uid":"821bc4e01b98bc19","reportUrl":"https://assurdly.github.io/northquest-automation-tests/86/67//#testresult/821bc4e01b98bc19","status":"passed","time":{"start":1744397279239,"stop":1744397279323,"duration":84}}]},"dc8a953637f4a59d9be568de31c57d9d:0a8f4e103c37037b363f6b883b97813d":{"statistic":{"failed":1,"broken":0,"skipped":0,"passed":0,"unknown":0,"total":1},"items":[{"uid":"5a12c437d76ec7ab","reportUrl":"https://assurdly.github.io/northquest-automation-tests/86/67//#testresult/5a12c437d76ec7ab","status":"failed","statusDetails":"Status code is 400","time":{"start":1744397272436,"stop":1744397272511,"duration":75}}]},"b2db30040f2d6e01d1fa65ca77264d94:b4154ced64812754009094d6fe606c77":{"statistic":{"failed":0,"broken":0,"skipped":0,"passed":1,"unknown":0,"total":1},"items":[{"uid":"666fee8389c9cd12","reportUrl":"https://assurdly.github.io/northquest-automation-tests/86/67//#testresult/666fee8389c9cd12","status":"passed","time":{"start":1744397265488,"stop":1744397265560,"duration":72}}]},"8e175e3223590900de08c29d11a2f9da:9acda0a901b8cd32cd0c491245e0782c":{"statistic":{"failed":1,"broken":0,"skipped":0,"passed":0,"unknown":0,"total":1},"items":[{"uid":"8271340102cc4561","reportUrl":"https://assurdly.github.io/northquest-automation-tests/86/67//#testresult/8271340102cc4561","status":"failed","statusDetails":"Status code is 400","time":{"start":1744397274934,"stop":1744397275128,"duration":194}}]},"3857020f7ccba4c6718f3c7300b1ab33:5e731fec419d993dd0245aebe172d292":{"statistic":{"failed":0,"broken":0,"skipped":0,"passed":1,"unknown":0,"total":1},"items":[{"uid":"7329d20931273aec","reportUrl":"https://assurdly.github.io/northquest-automation-tests/86/67//#testresult/7329d20931273aec","status":"passed","time":{"start":1744397262476,"stop":1744397262554,"duration":78}}]},"4ec37c63df4bfa8f91478f000c9aa265:65c14d54bb9b366f4f7b41b1222200dc":{"statistic":{"failed":1,"broken":0,"skipped":0,"passed":0,"unknown":0,"total":1},"items":[{"uid":"cc3d2c01056ccc71","reportUrl":"https://assurdly.github.io/northquest-automation-tests/86/67//#testresult/cc3d2c01056ccc71","status":"failed","statusDetails":"Status code is 200","time":{"start":1744397271433,"stop":1744397271534,"duration":101}}]},"afef76725f0fd522f1544c00c004258e:54f7b78c5ec1053bf4b4bb37b929eb43":{"statistic":{"failed":1,"broken":0,"skipped":0,"passed":0,"unknown":0,"total":1},"items":[{"uid":"5ca63f56d9074d4b","reportUrl":"https://assurdly.github.io/northquest-automation-tests/86/67//#testresult/5ca63f56d9074d4b","status":"failed","statusDetails":"Valid Error messages returned","time":{"start":1744397261468,"stop":1744397261550,"duration":82}}]},"7d5ede86f1c4ae517fba9166dc8b8a70:a7bb6214972cd2423e7542342fde0b43":{"statistic":{"failed":0,"broken":0,"skipped":0,"passed":1,"unknown":0,"total":1},"items":[{"uid":"2f0fe6778016c51","reportUrl":"https://assurdly.github.io/northquest-automation-tests/86/67//#testresult/2f0fe6778016c51","status":"passed","time":{"start":1744397264901,"stop":1744397264985,"duration":84}}]},"44aec06f444d659fc5359e8dce19e639:680e7228ba0e48d05899f86e4e0c6ea3":{"statistic":{"failed":1,"broken":0,"skipped":0,"passed":0,"unknown":0,"total":1},"items":[{"uid":"ece9ae21c5ee8892","reportUrl":"https://assurdly.github.io/northquest-automation-tests/86/67//#testresult/ece9ae21c5ee8892","status":"failed","statusDetails":"Status code is 200, Test for valid status, Test for valid response body","time":{"start":1744397279429,"stop":1744397279532,"duration":103}}]},"84db00942f9a86936a2340618578a7bf:21df20564051a1767485d06168bedfc7":{"statistic":{"failed":0,"broken":0,"skipped":0,"passed":1,"unknown":0,"total":1},"items":[{"uid":"f25c7e3980a8071","reportUrl":"https://assurdly.github.io/northquest-automation-tests/86/67//#testresult/f25c7e3980a8071","status":"passed","time":{"start":1744397281042,"stop":1744397281148,"duration":106}}]},"78043e0a3a8fd095cbb881ac45a4f938:d5f02de2cc2e44c35d504b48d9d26640":{"statistic":{"failed":0,"broken":0,"skipped":0,"passed":1,"unknown":0,"total":1},"items":[{"uid":"23f1a574b920fbbb","reportUrl":"https://assurdly.github.io/northquest-automation-tests/86/67//#testresult/23f1a574b920fbbb","status":"passed","time":{"start":1744397265335,"stop":1744397265410,"duration":75}}]},"fd095e4b91596101116a233094781941:abaee54957284588847a151169334c60":{"statistic":{"failed":0,"broken":0,"skipped":0,"passed":1,"unknown":0,"total":1},"items":[{"uid":"d5db098e3fe268e6","reportUrl":"https://assurdly.github.io/northquest-automation-tests/86/67//#testresult/d5db098e3fe268e6","status":"passed","time":{"start":1744397282629,"stop":1744397282741,"duration":112}}]},"14fd90b1061672ac6254d75edf5e5767:291f85c56485f7cc0c3afaa59ddc434c":{"statistic":{"failed":1,"broken":0,"skipped":0,"passed":0,"unknown":0,"total":1},"items":[{"uid":"81f7624adc2f2db0","reportUrl":"https://assurdly.github.io/northquest-automation-tests/86/67//#testresult/81f7624adc2f2db0","status":"failed","statusDetails":"Status code is 200","time":{"start":1744397271134,"stop":1744397271231,"duration":97}}]},"d887e15b2097ef4bdde97dd4dc17e35f:e10f615930cbcbbda6466d625e1d601c":{"statistic":{"failed":1,"broken":0,"skipped":0,"passed":0,"unknown":0,"total":1},"items":[{"uid":"1ba9c6338afe5c24","reportUrl":"https://assurdly.github.io/northquest-automation-tests/86/67//#testresult/1ba9c6338afe5c24","status":"failed","statusDetails":"Status code is 400, Test for valid error message","time":{"start":1744397269044,"stop":1744397269137,"duration":93}}]},"22319fe5525fd4ecc71229548d28179e:68e95e776df2c55db236c63cda53749a":{"statistic":{"failed":1,"broken":0,"skipped":0,"passed":0,"unknown":0,"total":1},"items":[{"uid":"187d78c33dfb6e6e","reportUrl":"https://assurdly.github.io/northquest-automation-tests/86/67//#testresult/187d78c33dfb6e6e","status":"failed","statusDetails":"Status code is 200","time":{"start":1744397271945,"stop":1744397272037,"duration":92}}]},"c76ce48ef0bc74c5ed6b35c046cc6393:6b214820c9d474dd3c1ce54b7905c921":{"statistic":{"failed":0,"broken":0,"skipped":0,"passed":1,"unknown":0,"total":1},"items":[{"uid":"e9a0ac31085c7692","reportUrl":"https://assurdly.github.io/northquest-automation-tests/86/67//#testresult/e9a0ac31085c7692","status":"passed","time":{"start":1744397266789,"stop":1744397266861,"duration":72}}]},"96a3739721bc0d353b78871e3feadfc8:50d8b3bd0d7ac0d1c73e0494bc0d3d6a":{"statistic":{"failed":1,"broken":0,"skipped":0,"passed":0,"unknown":0,"total":1},"items":[{"uid":"d9bd95e3757d63da","reportUrl":"https://assurdly.github.io/northquest-automation-tests/86/67//#testresult/d9bd95e3757d63da","status":"failed","statusDetails":"Status code is 200, Test for valid status, Test for valid error message","time":{"start":1744397278454,"stop":1744397278530,"duration":76}}]},"ec15cc48970b4b31feee71de9ac914a3:bc66eea122f538917b40ce45fe7beb43":{"statistic":{"failed":1,"broken":0,"skipped":0,"passed":0,"unknown":0,"total":1},"items":[{"uid":"4d922b417e32d657","reportUrl":"https://assurdly.github.io/northquest-automation-tests/86/67//#testresult/4d922b417e32d657","status":"failed","statusDetails":"Status code is 400, Test for valid error message","time":{"start":1744397265831,"stop":1744397265919,"duration":88}}]},"97de1b5ebce6458b2a18892861659e39:17abd6a439fd8558646685c429a6be8e":{"statistic":{"failed":1,"broken":0,"skipped":0,"passed":0,"unknown":0,"total":1},"items":[{"uid":"3a803c3690532bf7","reportUrl":"https://assurdly.github.io/northquest-automation-tests/86/67//#testresult/3a803c3690532bf7","status":"failed","statusDetails":"Status code is 400, Test for valid error message","time":{"start":1744397268936,"stop":1744397269041,"duration":105}}]},"75674467727d97beb309b47ee46a4804:ec2da1acc7fac50fda7d41c29abd3b36":{"statistic":{"failed":0,"broken":0,"skipped":0,"passed":1,"unknown":0,"total":1},"items":[{"uid":"a1aa7337a957639e","reportUrl":"https://assurdly.github.io/northquest-automation-tests/86/67//#testresult/a1aa7337a957639e","status":"passed","time":{"start":1744397267533,"stop":1744397267651,"duration":118}}]},"fe31d1dbc86c6f0fbd6580d9067ebf38:4e7f4ecfba6bac557e8cf5869aea0b84":{"statistic":{"failed":1,"broken":0,"skipped":0,"passed":0,"unknown":0,"total":1},"items":[{"uid":"7f00d53a467d834e","reportUrl":"https://assurdly.github.io/northquest-automation-tests/86/67//#testresult/7f00d53a467d834e","status":"failed","statusDetails":"Status code is 200 or 202, Valid status in response","time":{"start":1744397273536,"stop":1744397273648,"duration":112}}]},"1692aebae88f8b1f5b73a6f71f96ceb4:022af40f8bae7ac6be9f5cbb3d498c77":{"statistic":{"failed":0,"broken":0,"skipped":0,"passed":1,"unknown":0,"total":1},"items":[{"uid":"b981d43e5ab8eced","reportUrl":"https://assurdly.github.io/northquest-automation-tests/86/67//#testresult/b981d43e5ab8eced","status":"passed","time":{"start":1744397263727,"stop":1744397263806,"duration":79}}]},"3fe7a9cd4a02f15d39da1afbe99c6be0:2597aa81f5648494611d504ffdbd4876":{"statistic":{"failed":1,"broken":0,"skipped":0,"passed":0,"unknown":0,"total":1},"items":[{"uid":"3da7000b496073b3","reportUrl":"https://assurdly.github.io/northquest-automation-tests/86/67//#testresult/3da7000b496073b3","status":"failed","statusDetails":"Status code is 200","time":{"start":1744397271536,"stop":1744397271637,"duration":101}}]},"4681b80550affdd861957d06194fc5ba:7ed9cad6e18fd005c2ab371681e25393":{"statistic":{"failed":0,"broken":0,"skipped":0,"passed":1,"unknown":0,"total":1},"items":[{"uid":"32043e19242f5492","reportUrl":"https://assurdly.github.io/northquest-automation-tests/86/67//#testresult/32043e19242f5492","status":"passed","time":{"start":1744397264347,"stop":1744397264422,"duration":75}}]},"a09fc09464eee1c81dbd3449f243ae61:1cf67c310977ef6c619ed2c69ba65a5f":{"statistic":{"failed":1,"broken":0,"skipped":0,"passed":0,"unknown":0,"total":1},"items":[{"uid":"77f9d0b1beb6c56b","reportUrl":"https://assurdly.github.io/northquest-automation-tests/86/67//#testresult/77f9d0b1beb6c56b","status":"failed","statusDetails":"Status code is 200 or 202, Valid status in response","time":{"start":1744397276109,"stop":1744397276232,"duration":123}}]},"f1d27dd534c8dff9587169838b22707a:a0bd295d5149c68c4227543b50c88f18":{"statistic":{"failed":1,"broken":0,"skipped":0,"passed":0,"unknown":0,"total":1},"items":[{"uid":"3ea1976fc0da5","reportUrl":"https://assurdly.github.io/northquest-automation-tests/86/67//#testresult/3ea1976fc0da5","status":"failed","statusDetails":"Status code is 200 or 202, Valid status in response","time":{"start":1744397274132,"stop":1744397274233,"duration":101}}]},"5a9e3639f73e7b9a1d6f48474929c054:f4c14aedbac16a819d5e8f6dd08de293":{"statistic":{"failed":0,"broken":0,"skipped":0,"passed":1,"unknown":0,"total":1},"items":[{"uid":"ab50172bb4d75629","reportUrl":"https://assurdly.github.io/northquest-automation-tests/86/67//#testresult/ab50172bb4d75629","status":"passed","time":{"start":1744397263651,"stop":1744397263725,"duration":74}}]},"1e6f9f3ad380653e40aefb5f009bbf5a:42962534192b7caf2ab7b97acd77c4e6":{"statistic":{"failed":0,"broken":0,"skipped":0,"passed":1,"unknown":0,"total":1},"items":[{"uid":"5ed935d4d7b391b0","reportUrl":"https://assurdly.github.io/northquest-automation-tests/86/67//#testresult/5ed935d4d7b391b0","status":"passed","time":{"start":1744397281274,"stop":1744397281369,"duration":95}}]},"0c20f8fe5c6deb7397ed1400248e9de5:5b6b5fb54371c5d6a706a126c1c6f29f":{"statistic":{"failed":1,"broken":0,"skipped":0,"passed":0,"unknown":0,"total":1},"items":[{"uid":"93d2cbb94019380","reportUrl":"https://assurdly.github.io/northquest-automation-tests/86/67//#testresult/93d2cbb94019380","status":"failed","statusDetails":"Status code is 400","time":{"start":1744397272514,"stop":1744397272639,"duration":125}}]},"4c4d6a1d02d4a5840b406d53d7263c85:8837d5e124aa2f36b9efe3d59c8e5a2a":{"statistic":{"failed":1,"broken":0,"skipped":0,"passed":0,"unknown":0,"total":1},"items":[{"uid":"3b1d8069013d8c41","reportUrl":"https://assurdly.github.io/northquest-automation-tests/86/67//#testresult/3b1d8069013d8c41","status":"failed","statusDetails":"Status code is 200, Test for valid status","time":{"start":1744397277630,"stop":1744397277737,"duration":107}}]},"0e553bfd817fbde485960454a69b7b3c:faf7d2986d8564fee50a481fe66b9e54":{"statistic":{"failed":0,"broken":0,"skipped":0,"passed":1,"unknown":0,"total":1},"items":[{"uid":"edb364d097c18010","reportUrl":"https://assurdly.github.io/northquest-automation-tests/86/67//#testresult/edb364d097c18010","status":"passed","time":{"start":1744397281372,"stop":1744397281448,"duration":76}}]},"3859c09d35428acc58c1171388820b87:cd4274993fba3d32f8e36658f22a7423":{"statistic":{"failed":0,"broken":0,"skipped":0,"passed":1,"unknown":0,"total":1},"items":[{"uid":"7edef94db47a9c46","reportUrl":"https://assurdly.github.io/northquest-automation-tests/86/67//#testresult/7edef94db47a9c46","status":"passed","time":{"start":1744397278532,"stop":1744397278824,"duration":292}}]},"f9c89e83e757512d8bc3295b2ab0fe07:4a8026faab7718a003f642454759a499":{"statistic":{"failed":1,"broken":0,"skipped":0,"passed":0,"unknown":0,"total":1},"items":[{"uid":"fe4897738d7d7a05","reportUrl":"https://assurdly.github.io/northquest-automation-tests/86/67//#testresult/fe4897738d7d7a05","status":"failed","statusDetails":"Status code validation, Status code name has string, Test for valid error message","time":{"start":1744397262302,"stop":1744397262394,"duration":92}}]},"fcd3e83b1c1c59451d9c18faf2c3a089:f92507a6bd40de44fdeebcf5e2adf551":{"statistic":{"failed":0,"broken":0,"skipped":0,"passed":1,"unknown":0,"total":1},"items":[{"uid":"879ca23416b373d8","reportUrl":"https://assurdly.github.io/northquest-automation-tests/86/67//#testresult/879ca23416b373d8","status":"passed","time":{"start":1744397260528,"stop":1744397260613,"duration":85}}]},"761175ce35b4d3951668bd1e48df4ace:d618e0b315c134af8d9c32db0a03eadc":{"statistic":{"failed":0,"broken":0,"skipped":0,"passed":1,"unknown":0,"total":1},"items":[{"uid":"6e4a70185985df1d","reportUrl":"https://assurdly.github.io/northquest-automation-tests/86/67//#testresult/6e4a70185985df1d","status":"passed","time":{"start":1744397278331,"stop":1744397278451,"duration":120}}]},"a939bea688607a3bdc45a939aaddb874:422c24a612a989c7b0caad63142c4b01":{"statistic":{"failed":1,"broken":0,"skipped":0,"passed":0,"unknown":0,"total":1},"items":[{"uid":"be47840f6d8f7adc","reportUrl":"https://assurdly.github.io/northquest-automation-tests/86/67//#testresult/be47840f6d8f7adc","status":"failed","statusDetails":"Status code is 400, Test for valid error message","time":{"start":1744397276858,"stop":1744397277039,"duration":181}}]},"4f1ea809b5c24b31acc8188899a82f39:88c95d9f085aaf6ebff20100d6fddb52":{"statistic":{"failed":0,"broken":0,"skipped":0,"passed":1,"unknown":0,"total":1},"items":[{"uid":"a752f8181ee36bb1","reportUrl":"https://assurdly.github.io/northquest-automation-tests/86/67//#testresult/a752f8181ee36bb1","status":"passed","time":{"start":1744397281856,"stop":1744397281972,"duration":116}}]},"71cfefd2767e33569008299c35a193a7:b9855ea962379312cb2697ea7cc793e7":{"statistic":{"failed":0,"broken":0,"skipped":0,"passed":1,"unknown":0,"total":1},"items":[{"uid":"1be88a9c554bd419","reportUrl":"https://assurdly.github.io/northquest-automation-tests/86/67//#testresult/1be88a9c554bd419","status":"passed","time":{"start":1744397264826,"stop":1744397264898,"duration":72}}]},"e1496a932d399ba2cd18ad95361702e8:e55622425bcd0c773da5dd9be4fb1211":{"statistic":{"failed":1,"broken":0,"skipped":0,"passed":0,"unknown":0,"total":1},"items":[{"uid":"7dec3f600d86091d","reportUrl":"https://assurdly.github.io/northquest-automation-tests/86/67//#testresult/7dec3f600d86091d","status":"failed","statusDetails":"Status code is 200 or 202, Valid status in response","time":{"start":1744397274810,"stop":1744397274932,"duration":122}}]},"e1600f48627068ed6862bbc275edc81f:7621b77c21bf7176a813e96418e334c1":{"statistic":{"failed":1,"broken":0,"skipped":0,"passed":0,"unknown":0,"total":1},"items":[{"uid":"392e42b87dc7047b","reportUrl":"https://assurdly.github.io/northquest-automation-tests/86/67//#testresult/392e42b87dc7047b","status":"failed","statusDetails":"Status code is 400, Test for valid error message","time":{"start":1744397277740,"stop":1744397277833,"duration":93}}]},"874b3d3974572fc8e6b297b2b5eab485:54f7b78c5ec1053bf4b4bb37b929eb43":{"statistic":{"failed":0,"broken":0,"skipped":0,"passed":1,"unknown":0,"total":1},"items":[{"uid":"2905bb451328573c","reportUrl":"https://assurdly.github.io/northquest-automation-tests/86/67//#testresult/2905bb451328573c","status":"passed","time":{"start":1744397261161,"stop":1744397261241,"duration":80}}]},"200228d5f4e033bdb50808e7aa42ca3c:810c1b40d8248987f1736d3328d7b2e1":{"statistic":{"failed":0,"broken":0,"skipped":0,"passed":1,"unknown":0,"total":1},"items":[{"uid":"a18c6a0c2746b26e","reportUrl":"https://assurdly.github.io/northquest-automation-tests/86/67//#testresult/a18c6a0c2746b26e","status":"passed","time":{"start":1744397272716,"stop":1744397272829,"duration":113}}]},"f96e97f5c5414c51668a9c2b928d3bcd:aee2c59d4146ada7bd55fa7af78c731a":{"statistic":{"failed":0,"broken":0,"skipped":0,"passed":1,"unknown":0,"total":1},"items":[{"uid":"d57d952ee8d3e367","reportUrl":"https://assurdly.github.io/northquest-automation-tests/86/67//#testresult/d57d952ee8d3e367","status":"passed","time":{"start":1744397273130,"stop":1744397273223,"duration":93}}]},"93a24973e07751dcc2ed85f2c1f33807:4ed5e59eb1df0d81fb6a6488b62eca0a":{"statistic":{"failed":0,"broken":0,"skipped":0,"passed":1,"unknown":0,"total":1},"items":[{"uid":"3362035e910333fa","reportUrl":"https://assurdly.github.io/northquest-automation-tests/86/67//#testresult/3362035e910333fa","status":"passed","time":{"start":1744397282057,"stop":1744397282133,"duration":76}}]},"f2ce00011064e6613e585d2b03ba62cb:64273ce055fd8486196c515ccc54d058":{"statistic":{"failed":0,"broken":0,"skipped":0,"passed":1,"unknown":0,"total":1},"items":[{"uid":"9dfd359cbbfff381","reportUrl":"https://assurdly.github.io/northquest-automation-tests/86/67//#testresult/9dfd359cbbfff381","status":"passed","time":{"start":1744397279129,"stop":1744397279236,"duration":107}}]},"9a87231aa65b4041b95fb82d8546471e:aec95881be18230685a253d959991a78":{"statistic":{"failed":0,"broken":0,"skipped":0,"passed":1,"unknown":0,"total":1},"items":[{"uid":"7ca9796a8cf7501","reportUrl":"https://assurdly.github.io/northquest-automation-tests/86/67//#testresult/7ca9796a8cf7501","status":"passed","time":{"start":1744397263968,"stop":1744397264043,"duration":75}}]},"8659ea2b3f2a9a9c241149986218966d:a7bb6214972cd2423e7542342fde0b43":{"statistic":{"failed":0,"broken":0,"skipped":0,"passed":1,"unknown":0,"total":1},"items":[{"uid":"45047227c3a9ae1b","reportUrl":"https://assurdly.github.io/northquest-automation-tests/86/67//#testresult/45047227c3a9ae1b","status":"passed","time":{"start":1744397265177,"stop":1744397265252,"duration":75}}]},"913e80bd6bb0e72b1579f9c6375360b8:14a1d9e490c7f2aa90c8e19bf41a6035":{"statistic":{"failed":0,"broken":0,"skipped":0,"passed":1,"unknown":0,"total":1},"items":[{"uid":"6318b0df2353bd0b","reportUrl":"https://assurdly.github.io/northquest-automation-tests/86/67//#testresult/6318b0df2353bd0b","status":"passed","time":{"start":1744397271036,"stop":1744397271131,"duration":95}}]},"bbe3b587b5d98632d64bbbf34238b2d6:71932cb08d3f467c3a4f7c065cdae20e":{"statistic":{"failed":1,"broken":0,"skipped":0,"passed":0,"unknown":0,"total":1},"items":[{"uid":"629e818a2008dc0d","reportUrl":"https://assurdly.github.io/northquest-automation-tests/86/67//#testresult/629e818a2008dc0d","status":"failed","statusDetails":"Tests for successfull Request, Status code is 200","time":{"start":1744397263227,"stop":1744397263308,"duration":81}}]},"be33d3e35b0c346bde77fba3729ee76f:cb7672a73f3e316500c85c3191091a7d":{"statistic":{"failed":0,"broken":0,"skipped":0,"passed":1,"unknown":0,"total":1},"items":[{"uid":"6922486ed8a01b4d","reportUrl":"https://assurdly.github.io/northquest-automation-tests/86/67//#testresult/6922486ed8a01b4d","status":"passed","time":{"start":1744397276037,"stop":1744397276107,"duration":70}}]},"38a4728eff67e98abf99973e02f0598a:a7ba4a4c0bf53ee184a14dbc0eedcd7b":{"statistic":{"failed":0,"broken":0,"skipped":0,"passed":1,"unknown":0,"total":1},"items":[{"uid":"d70966c5c60eaa10","reportUrl":"https://assurdly.github.io/northquest-automation-tests/86/67//#testresult/d70966c5c60eaa10","status":"passed","time":{"start":1744397282908,"stop":1744397283634,"duration":726}}]},"619bde5f5fd8d6fff23fe37a693b5528:93f6218c11a08cd9860f03744f28f30f":{"statistic":{"failed":1,"broken":0,"skipped":0,"passed":0,"unknown":0,"total":1},"items":[{"uid":"24dfc2c1578265e4","reportUrl":"https://assurdly.github.io/northquest-automation-tests/86/67//#testresult/24dfc2c1578265e4","status":"failed","statusDetails":"Status code is 200","time":{"start":1744397270742,"stop":1744397270832,"duration":90}}]},"17efe49ebf204120fea561e7b0580557:120b38c0afee01d0426d71e54a4f65e0":{"statistic":{"failed":1,"broken":0,"skipped":0,"passed":0,"unknown":0,"total":1},"items":[{"uid":"4190aec13de6d63a","reportUrl":"https://assurdly.github.io/northquest-automation-tests/86/67//#testresult/4190aec13de6d63a","status":"failed","statusDetails":"Status code is 400, Test for valid error message","time":{"start":1744397266326,"stop":1744397266403,"duration":77}}]},"2329e256c8d3b19cd21e70a9cae8c8ad:0732d0cb9a8b2ff8831301211aa414c8":{"statistic":{"failed":1,"broken":0,"skipped":0,"passed":0,"unknown":0,"total":1},"items":[{"uid":"c53aa54b5b628c69","reportUrl":"https://assurdly.github.io/northquest-automation-tests/86/67//#testresult/c53aa54b5b628c69","status":"failed","statusDetails":"Status code is 200, Test for valid status, Test for valid error message","time":{"start":1744397270433,"stop":1744397270533,"duration":100}}]},"3150185660568832897e47a45463b108:b75ec150b1ce16070283601f53ea6564":{"statistic":{"failed":0,"broken":0,"skipped":0,"passed":1,"unknown":0,"total":1},"items":[{"uid":"ed676c61b8c4e761","reportUrl":"https://assurdly.github.io/northquest-automation-tests/86/67//#testresult/ed676c61b8c4e761","status":"passed","time":{"start":1744397264045,"stop":1744397264118,"duration":73}}]},"cec6a1aab3adcf78db807509d13ed7f5:c46dddcf5cf7e4fdd92052c7b486f24c":{"statistic":{"failed":1,"broken":0,"skipped":0,"passed":0,"unknown":0,"total":1},"items":[{"uid":"ee9e7b8b8b2b0e18","reportUrl":"https://assurdly.github.io/northquest-automation-tests/86/67//#testresult/ee9e7b8b8b2b0e18","status":"failed","statusDetails":"Status code is 400, Test for valid error message","time":{"start":1744397266080,"stop":1744397266154,"duration":74}}]},"47a71ea05e3a2f1be5c2520ad02a39aa:f92507a6bd40de44fdeebcf5e2adf551":{"statistic":{"failed":0,"broken":0,"skipped":0,"passed":1,"unknown":0,"total":1},"items":[{"uid":"17ff30af3a069a19","reportUrl":"https://assurdly.github.io/northquest-automation-tests/86/67//#testresult/17ff30af3a069a19","status":"passed","time":{"start":1744397260324,"stop":1744397260437,"duration":113}}]},"fe6059d3dad5179f3e4b8bffc3fdfc48:3607e707551300810cc838457d7b0ef4":{"statistic":{"failed":1,"broken":0,"skipped":0,"passed":0,"unknown":0,"total":1},"items":[{"uid":"5dd53c6c175cfb21","reportUrl":"https://assurdly.github.io/northquest-automation-tests/86/67//#testresult/5dd53c6c175cfb21","status":"failed","statusDetails":"Status code is 400, Test for valid error message","time":{"start":1744397269539,"stop":1744397269641,"duration":102}}]},"85748d59804ec5c4e2380e223414ddd1:9674f66c92a3cd192869ccbd048136a1":{"statistic":{"failed":0,"broken":0,"skipped":0,"passed":1,"unknown":0,"total":1},"items":[{"uid":"e4c68eb704a11332","reportUrl":"https://assurdly.github.io/northquest-automation-tests/86/67//#testresult/e4c68eb704a11332","status":"passed","time":{"start":1744397283706,"stop":1744397284041,"duration":335}}]},"05d675eca2be551c191d959d759b48a0:5e731fec419d993dd0245aebe172d292":{"statistic":{"failed":0,"broken":0,"skipped":0,"passed":1,"unknown":0,"total":1},"items":[{"uid":"f17b3d41d7e93923","reportUrl":"https://assurdly.github.io/northquest-automation-tests/86/67//#testresult/f17b3d41d7e93923","status":"passed","time":{"start":1744397262635,"stop":1744397262718,"duration":83}}]},"28b4de0d8f4f956d40a60f6aafb45405:f39da1bad4775ede7c42f66fd7c263ce":{"statistic":{"failed":1,"broken":0,"skipped":0,"passed":0,"unknown":0,"total":1},"items":[{"uid":"aa70ef06d3f20a11","reportUrl":"https://assurdly.github.io/northquest-automation-tests/86/67//#testresult/aa70ef06d3f20a11","status":"failed","statusDetails":"Status code is 400","time":{"start":1744397274632,"stop":1744397274732,"duration":100}}]},"54a681585fddeb947eb6d9c833088d8d:4d8ba03d422f27c311a0e366ac08482e":{"statistic":{"failed":1,"broken":0,"skipped":0,"passed":0,"unknown":0,"total":1},"items":[{"uid":"d9a1068d20450e4b","reportUrl":"https://assurdly.github.io/northquest-automation-tests/86/67//#testresult/d9a1068d20450e4b","status":"failed","statusDetails":"Status code is 200, Test for valid status","time":{"start":1744397266556,"stop":1744397266629,"duration":73}}]},"a7d29408d7f31206ba22a6001f4ab8fc:022af40f8bae7ac6be9f5cbb3d498c77":{"statistic":{"failed":0,"broken":0,"skipped":0,"passed":1,"unknown":0,"total":1},"items":[{"uid":"63852124f5d6a048","reportUrl":"https://assurdly.github.io/northquest-automation-tests/86/67//#testresult/63852124f5d6a048","status":"passed","time":{"start":1744397261553,"stop":1744397261648,"duration":95}}]},"d3907c45ee1306085c74f70e6c050850:68e95e776df2c55db236c63cda53749a":{"statistic":{"failed":1,"broken":0,"skipped":0,"passed":0,"unknown":0,"total":1},"items":[{"uid":"d7fac3ce9a8a9f8","reportUrl":"https://assurdly.github.io/northquest-automation-tests/86/67//#testresult/d7fac3ce9a8a9f8","status":"failed","statusDetails":"Status code is 200","time":{"start":1744397272040,"stop":1744397272272,"duration":232}}]},"dfa0c85693c9442b72b5fffaae29c191:f92507a6bd40de44fdeebcf5e2adf551":{"statistic":{"failed":0,"broken":0,"skipped":0,"passed":1,"unknown":0,"total":1},"items":[{"uid":"e2ab363eee723cb5","reportUrl":"https://assurdly.github.io/northquest-automation-tests/86/67//#testresult/e2ab363eee723cb5","status":"passed","time":{"start":1744397260697,"stop":1744397260779,"duration":82}}]},"7a7b211bb807a1b12b0ba405a0749f8a:d01ce786b7ad4d7b21298495c1200dd8":{"statistic":{"failed":1,"broken":0,"skipped":0,"passed":0,"unknown":0,"total":1},"items":[{"uid":"23e00855b52c8af4","reportUrl":"https://assurdly.github.io/northquest-automation-tests/86/67//#testresult/23e00855b52c8af4","status":"failed","statusDetails":"Status code is 200, Test for valid status, Test for data structure","time":{"start":1744397276745,"stop":1744397276856,"duration":111}}]},"f88d28ba098ca61fc3e351cd978f97bc:5079032bf07ff79105b4fef8ec176fed":{"statistic":{"failed":1,"broken":0,"skipped":0,"passed":0,"unknown":0,"total":1},"items":[{"uid":"789d1126895d7c0b","reportUrl":"https://assurdly.github.io/northquest-automation-tests/86/67//#testresult/789d1126895d7c0b","status":"failed","statusDetails":"Status code is 400","time":{"start":1744397268544,"stop":1744397268629,"duration":85}}]},"73f7b2ae086f67639ca9db6d7ff0fad2:bfbdaf9c62af851f0d5e7b3fc52e81a4":{"statistic":{"failed":1,"broken":0,"skipped":0,"passed":0,"unknown":0,"total":1},"items":[{"uid":"79d7460217af093d","reportUrl":"https://assurdly.github.io/northquest-automation-tests/86/67//#testresult/79d7460217af093d","status":"failed","statusDetails":"Status code is 400","time":{"start":1744397275207,"stop":1744397275332,"duration":125}}]},"d50aa2f71d726c534d0c44416e1d5aa7:2a7de9d6bd90abdc01d28476057c9294":{"statistic":{"failed":0,"broken":0,"skipped":0,"passed":1,"unknown":0,"total":1},"items":[{"uid":"dde3f9e8a9bc1ad8","reportUrl":"https://assurdly.github.io/northquest-automation-tests/86/67//#testresult/dde3f9e8a9bc1ad8","status":"passed","time":{"start":1744397281151,"stop":1744397281271,"duration":120}}]},"a21d76460ed52af10a72557ac24b0b14:990d0670189098ed720e6600f19f3a53":{"statistic":{"failed":1,"broken":0,"skipped":0,"passed":0,"unknown":0,"total":1},"items":[{"uid":"3c2ca27f5278a68e","reportUrl":"https://assurdly.github.io/northquest-automation-tests/86/67//#testresult/3c2ca27f5278a68e","status":"failed","statusDetails":"Test for valid error message","time":{"start":1744397279932,"stop":1744397280056,"duration":124}}]},"54467365b05e04b135e50e59eedf07fa:cef688dc08861007fdb049df4bb30738":{"statistic":{"failed":0,"broken":0,"skipped":0,"passed":1,"unknown":0,"total":1},"items":[{"uid":"d8e17591e2028147","reportUrl":"https://assurdly.github.io/northquest-automation-tests/86/67//#testresult/d8e17591e2028147","status":"passed","time":{"start":1744397281975,"stop":1744397282054,"duration":79}}]},"086f75de81688906bfe4e3a7092c708c:c4f80cc68d1c0d13c250b2945fdaad67":{"statistic":{"failed":1,"broken":0,"skipped":0,"passed":0,"unknown":0,"total":1},"items":[{"uid":"f76a24d499534819","reportUrl":"https://assurdly.github.io/northquest-automation-tests/86/67//#testresult/f76a24d499534819","status":"failed","statusDetails":"Test for valid error message","time":{"start":1744397277437,"stop":1744397277627,"duration":190}}]},"c87fd62c62bd416625c679fcb70721fc:a7bb6214972cd2423e7542342fde0b43":{"statistic":{"failed":1,"broken":0,"skipped":0,"passed":0,"unknown":0,"total":1},"items":[{"uid":"1f7f6eda7519b464","reportUrl":"https://assurdly.github.io/northquest-automation-tests/86/67//#testresult/1f7f6eda7519b464","status":"failed","statusDetails":"Tests for Invalid old password, Status code is 400","time":{"start":1744397264988,"stop":1744397265096,"duration":108}}]},"a58f31645bb8967e8318e371a3a19291:eed5bcb602406c5a4a93239bb9d3be3f":{"statistic":{"failed":1,"broken":0,"skipped":0,"passed":0,"unknown":0,"total":1},"items":[{"uid":"232e39f6534487b3","reportUrl":"https://assurdly.github.io/northquest-automation-tests/86/67//#testresult/232e39f6534487b3","status":"failed","statusDetails":"Status code is 400, Test for valid error message","time":{"start":1744397268140,"stop":1744397268241,"duration":101}}]},"cbd8431bc3bff2cc223a6d7afc6216c1:0e78d2c0ba5b9098dd653866d11862f5":{"statistic":{"failed":1,"broken":0,"skipped":0,"passed":0,"unknown":0,"total":1},"items":[{"uid":"caed730a02794d7b","reportUrl":"https://assurdly.github.io/northquest-automation-tests/86/67//#testresult/caed730a02794d7b","status":"failed","statusDetails":"Status code is 200, Test for valid status","time":{"start":1744397270145,"stop":1744397270235,"duration":90}}]},"506b508acb72b90152b472ba2241d634:59e9a4885a232a6578ff702ac87274e8":{"statistic":{"failed":0,"broken":0,"skipped":0,"passed":1,"unknown":0,"total":1},"items":[{"uid":"7bf07de4c58e8ac2","reportUrl":"https://assurdly.github.io/northquest-automation-tests/86/67//#testresult/7bf07de4c58e8ac2","status":"passed","time":{"start":1744397281568,"stop":1744397281677,"duration":109}}]},"d529fe3234287670726e95007c258f8f:b1d2595daf683465050f3f0fed49e4e6":{"statistic":{"failed":0,"broken":0,"skipped":0,"passed":1,"unknown":0,"total":1},"items":[{"uid":"bfd59c6f899f46da","reportUrl":"https://assurdly.github.io/northquest-automation-tests/86/67//#testresult/bfd59c6f899f46da","status":"passed","time":{"start":1744397280240,"stop":1744397280328,"duration":88}}]},"5a78e4627dc717a931c5f8ef1d1b7a6e:94fd0a5d462c13e999040bb29822c5b4":{"statistic":{"failed":0,"broken":0,"skipped":0,"passed":1,"unknown":0,"total":1},"items":[{"uid":"c9346c4ff2255d0b","reportUrl":"https://assurdly.github.io/northquest-automation-tests/86/67//#testresult/c9346c4ff2255d0b","status":"passed","time":{"start":1744397265563,"stop":1744397265637,"duration":74}}]},"da4e3761212537af995056f6b635fa61:bbf92e9899a62a525a4706acc0e4c934":{"statistic":{"failed":1,"broken":0,"skipped":0,"passed":0,"unknown":0,"total":1},"items":[{"uid":"6b0bd87ac9a78e4c","reportUrl":"https://assurdly.github.io/northquest-automation-tests/86/67//#testresult/6b0bd87ac9a78e4c","status":"failed","statusDetails":"Status code is 200","time":{"start":1744397271756,"stop":1744397271836,"duration":80}}]},"e8c52eba2f7d79a08ef2740b9a803af6:3caf2ca4f91c42e8bd1a192af556e021":{"statistic":{"failed":0,"broken":0,"skipped":0,"passed":1,"unknown":0,"total":1},"items":[{"uid":"106f57c4a4f92483","reportUrl":"https://assurdly.github.io/northquest-automation-tests/86/67//#testresult/106f57c4a4f92483","status":"passed","time":{"start":1744397280058,"stop":1744397280138,"duration":80}}]},"62543513b7bda47b6d0b22c50b1e1891:b35f5a14fcbccaeab29c1f4ca6f2f89a":{"statistic":{"failed":0,"broken":0,"skipped":0,"passed":1,"unknown":0,"total":1},"items":[{"uid":"80b110d286dcc6f2","reportUrl":"https://assurdly.github.io/northquest-automation-tests/86/67//#testresult/80b110d286dcc6f2","status":"passed","time":{"start":1744397269939,"stop":1744397270029,"duration":90}}]},"bf8675fb5b23ddd7483bbde8a5515162:990d0670189098ed720e6600f19f3a53":{"statistic":{"failed":0,"broken":0,"skipped":0,"passed":1,"unknown":0,"total":1},"items":[{"uid":"1b95e904ed0463e3","reportUrl":"https://assurdly.github.io/northquest-automation-tests/86/67//#testresult/1b95e904ed0463e3","status":"passed","time":{"start":1744397279660,"stop":1744397279731,"duration":71}}]},"8d2400aecaa2f964fac9dafa1587b2fd:5079032bf07ff79105b4fef8ec176fed":{"statistic":{"failed":1,"broken":0,"skipped":0,"passed":0,"unknown":0,"total":1},"items":[{"uid":"b1a7200785cf1c24","reportUrl":"https://assurdly.github.io/northquest-automation-tests/86/67//#testresult/b1a7200785cf1c24","status":"failed","statusDetails":"Status code is 409, Test for valid error message","time":{"start":1744397268340,"stop":1744397268454,"duration":114}}]},"c37a2dc116944e988f3000debc464f09:f169b9eff6a23b0707824bafa4706657":{"statistic":{"failed":1,"broken":0,"skipped":0,"passed":0,"unknown":0,"total":1},"items":[{"uid":"736dc6675a9dcf8f","reportUrl":"https://assurdly.github.io/northquest-automation-tests/86/67//#testresult/736dc6675a9dcf8f","status":"failed","statusDetails":"Status code is 200 or 202, Valid status in response","time":{"start":1744397273934,"stop":1744397274029,"duration":95}}]},"154f0d591cdcb46dd2bd8ff83bb1c8ab:cc2f9d884f2d2ce9f990851185a27967":{"statistic":{"failed":1,"broken":0,"skipped":0,"passed":0,"unknown":0,"total":1},"items":[{"uid":"402820dfc3f32355","reportUrl":"https://assurdly.github.io/northquest-automation-tests/86/67//#testresult/402820dfc3f32355","status":"failed","statusDetails":"Status code is 200, Test for valid status, Test for valid error message","time":{"start":1744397270238,"stop":1744397270331,"duration":93}}]},"5a4c492c716fb407280d388fc9715763:e62261a19befeb9ffa2f9b5a6884ce84":{"statistic":{"failed":0,"broken":0,"skipped":0,"passed":1,"unknown":0,"total":1},"items":[{"uid":"6baf7a1ef7a52fe3","reportUrl":"https://assurdly.github.io/northquest-automation-tests/86/67//#testresult/6baf7a1ef7a52fe3","status":"passed","time":{"start":1744397276637,"stop":1744397276742,"duration":105}}]},"f9265811b02babb9ff8708b383b00fd2:69e203f1c2939da15c2b533a524c6b64":{"statistic":{"failed":0,"broken":0,"skipped":0,"passed":1,"unknown":0,"total":1},"items":[{"uid":"67193ff7287e5c57","reportUrl":"https://assurdly.github.io/northquest-automation-tests/86/67//#testresult/67193ff7287e5c57","status":"passed","time":{"start":1744397267240,"stop":1744397267332,"duration":92}}]},"2e1d5e91a3bbffc05e9ca776f574ca16:91a15240af237f6424626a459f3b98cf":{"statistic":{"failed":1,"broken":0,"skipped":0,"passed":0,"unknown":0,"total":1},"items":[{"uid":"39409f893e41e746","reportUrl":"https://assurdly.github.io/northquest-automation-tests/86/67//#testresult/39409f893e41e746","status":"failed","statusDetails":"Status code is 400","time":{"start":1744397275731,"stop":1744397275828,"duration":97}}]},"5a4c492c716fb407280d388fc9715763:bcb047dc322754a67e951c71996b8288":{"statistic":{"failed":0,"broken":0,"skipped":0,"passed":1,"unknown":0,"total":1},"items":[{"uid":"2faa2bc81b4961ab","reportUrl":"https://assurdly.github.io/northquest-automation-tests/86/67//#testresult/2faa2bc81b4961ab","status":"passed","time":{"start":1744397276235,"stop":1744397276336,"duration":101}}]},"b54f85a6f58fa56a5f34b16f1ef7f1d2:9cb57d32f0acdef7f66c3d088cda3cb2":{"statistic":{"failed":0,"broken":0,"skipped":0,"passed":1,"unknown":0,"total":1},"items":[{"uid":"e6f7227cc651c6c","reportUrl":"https://assurdly.github.io/northquest-automation-tests/86/67//#testresult/e6f7227cc651c6c","status":"passed","time":{"start":1744397269841,"stop":1744397269937,"duration":96}}]},"789c03264e801d3fa0df3e19306b4ecb:520863eac04e938ec4666e14cfcc0cea":{"statistic":{"failed":1,"broken":0,"skipped":0,"passed":0,"unknown":0,"total":1},"items":[{"uid":"1799f79cc20ce9c","reportUrl":"https://assurdly.github.io/northquest-automation-tests/86/67//#testresult/1799f79cc20ce9c","status":"failed","statusDetails":"Status code is 200, Test for valid status, Test for valid error message","time":{"start":1744397270636,"stop":1744397270740,"duration":104}}]},"87bddd0a15256e176190fb0414350ac0:a4807f43a605960882f887145f5c9375":{"statistic":{"failed":0,"broken":0,"skipped":0,"passed":1,"unknown":0,"total":1},"items":[{"uid":"26bbbeb7dfdbd467","reportUrl":"https://assurdly.github.io/northquest-automation-tests/86/67//#testresult/26bbbeb7dfdbd467","status":"passed","time":{"start":1744397268834,"stop":1744397268934,"duration":100}}]},"5822a77aed022229b770ffe30a9ff984:fe867480c21e51780f490128ab0391d7":{"statistic":{"failed":0,"broken":0,"skipped":0,"passed":1,"unknown":0,"total":1},"items":[{"uid":"5d4e2a466ecd70d3","reportUrl":"https://assurdly.github.io/northquest-automation-tests/86/67//#testresult/5d4e2a466ecd70d3","status":"passed","time":{"start":1744397259554,"stop":1744397260014,"duration":460}}]},"1e9e34d43d9279fe90aaea347d8ef306:54f7b78c5ec1053bf4b4bb37b929eb43":{"statistic":{"failed":0,"broken":0,"skipped":0,"passed":1,"unknown":0,"total":1},"items":[{"uid":"a93f804eb93c2fd5","reportUrl":"https://assurdly.github.io/northquest-automation-tests/86/67//#testresult/a93f804eb93c2fd5","status":"passed","time":{"start":1744397260782,"stop":1744397261157,"duration":375}}]},"08ad175248808246ffffe043e6ae48a8:b6339489c29643525f9e9f18f126519d":{"statistic":{"failed":0,"broken":0,"skipped":0,"passed":1,"unknown":0,"total":1},"items":[{"uid":"12485e89319b0611","reportUrl":"https://assurdly.github.io/northquest-automation-tests/86/67//#testresult/12485e89319b0611","status":"passed","time":{"start":1744397277041,"stop":1744397277229,"duration":188}}]},"d71b3b4865a2a376c831ed8e79cf7582:f4c14aedbac16a819d5e8f6dd08de293":{"statistic":{"failed":0,"broken":0,"skipped":0,"passed":1,"unknown":0,"total":1},"items":[{"uid":"28adbc83be03e27f","reportUrl":"https://assurdly.github.io/northquest-automation-tests/86/67//#testresult/28adbc83be03e27f","status":"passed","time":{"start":1744397263570,"stop":1744397263649,"duration":79}}]},"972de3c98c56392d6de43c47ee3e50e7:9e1762dc583eb26c76a30deef69419b0":{"statistic":{"failed":1,"broken":0,"skipped":0,"passed":0,"unknown":0,"total":1},"items":[{"uid":"a5143f51d859345c","reportUrl":"https://assurdly.github.io/northquest-automation-tests/86/67//#testresult/a5143f51d859345c","status":"failed","statusDetails":"Status code is 400, Test for valid error message","time":{"start":1744397269236,"stop":1744397269341,"duration":105}}]},"6f81f3bfc928bdc3c276b5e6ab95dd24:517f42c9ee4a2cafb2d849428ad252eb":{"statistic":{"failed":0,"broken":0,"skipped":0,"passed":1,"unknown":0,"total":1},"items":[{"uid":"62f0e023a77bfac6","reportUrl":"https://assurdly.github.io/northquest-automation-tests/86/67//#testresult/62f0e023a77bfac6","status":"passed","time":{"start":1744397278231,"stop":1744397278329,"duration":98}}]},"3cf14ae593bf42b9812d70e1e5e7e822:843415d7808b452230143aad9c7426ba":{"statistic":{"failed":0,"broken":0,"skipped":0,"passed":1,"unknown":0,"total":1},"items":[{"uid":"7c4959b0cbb06451","reportUrl":"https://assurdly.github.io/northquest-automation-tests/86/67//#testresult/7c4959b0cbb06451","status":"passed","time":{"start":1744397269741,"stop":1744397269838,"duration":97}}]},"9ee6cf6d49349467fa9ab40da3e54dcc:c721f117a99e49e2bf84a0247dbf78a5":{"statistic":{"failed":0,"broken":0,"skipped":0,"passed":1,"unknown":0,"total":1},"items":[{"uid":"f32f27b88869fbe3","reportUrl":"https://assurdly.github.io/northquest-automation-tests/86/67//#testresult/f32f27b88869fbe3","status":"passed","time":{"start":1744397270333,"stop":1744397270430,"duration":97}}]},"96b58fb49ae5d683781c8395efa88fe7:5e731fec419d993dd0245aebe172d292":{"statistic":{"failed":1,"broken":0,"skipped":0,"passed":0,"unknown":0,"total":1},"items":[{"uid":"148e49e57f299bf3","reportUrl":"https://assurdly.github.io/northquest-automation-tests/86/67//#testresult/148e49e57f299bf3","status":"failed","statusDetails":"Successful POST request, Test for valid error message","time":{"start":1744397263138,"stop":1744397263224,"duration":86}}]},"756b0b4f2c5d3733a33ef6bb6c2f62e5:9c2678e46f1691912dc31db9817c2a3a":{"statistic":{"failed":0,"broken":0,"skipped":0,"passed":1,"unknown":0,"total":1},"items":[{"uid":"411efc3f1d0b774c","reportUrl":"https://assurdly.github.io/northquest-automation-tests/86/67//#testresult/411efc3f1d0b774c","status":"passed","time":{"start":1744397266713,"stop":1744397266787,"duration":74}}]},"8bb2198a45837d86136a70313a3d07aa:990d0670189098ed720e6600f19f3a53":{"statistic":{"failed":1,"broken":0,"skipped":0,"passed":0,"unknown":0,"total":1},"items":[{"uid":"9588d490c7a09d6","reportUrl":"https://assurdly.github.io/northquest-automation-tests/86/67//#testresult/9588d490c7a09d6","status":"failed","statusDetails":"Test for valid error message","time":{"start":1744397279734,"stop":1744397279830,"duration":96}}]},"268d8ca927eaa5227c88deb98e7fd8e2:71932cb08d3f467c3a4f7c065cdae20e":{"statistic":{"failed":0,"broken":0,"skipped":0,"passed":1,"unknown":0,"total":1},"items":[{"uid":"b9e6a39492dcf865","reportUrl":"https://assurdly.github.io/northquest-automation-tests/86/67//#testresult/b9e6a39492dcf865","status":"passed","time":{"start":1744397263044,"stop":1744397263136,"duration":92}}]},"2575d0a0d86f9dde23e39c891aa13f7d:5079032bf07ff79105b4fef8ec176fed":{"statistic":{"failed":1,"broken":0,"skipped":0,"passed":0,"unknown":0,"total":1},"items":[{"uid":"571539a84d016aa7","reportUrl":"https://assurdly.github.io/northquest-automation-tests/86/67//#testresult/571539a84d016aa7","status":"failed","statusDetails":"Status code is 400, Test for valid error message","time":{"start":1744397268632,"stop":1744397268740,"duration":108}}]},"d0b4067b1996ccaa35265ed0d5c43763:fc32ac05585ffb47ce95762170268f30":{"statistic":{"failed":0,"broken":0,"skipped":0,"passed":1,"unknown":0,"total":1},"items":[{"uid":"5865425e53b8ff80","reportUrl":"https://assurdly.github.io/northquest-automation-tests/86/67//#testresult/5865425e53b8ff80","status":"passed","time":{"start":1744397279024,"stop":1744397279126,"duration":102}}]},"8dc4265a9bdc3257045b53d5efad18d8:c616b6288b0a642f640cf4dac39cd5c9":{"statistic":{"failed":0,"broken":0,"skipped":0,"passed":1,"unknown":0,"total":1},"items":[{"uid":"e69b1c5839ae0e00","reportUrl":"https://assurdly.github.io/northquest-automation-tests/86/67//#testresult/e69b1c5839ae0e00","status":"passed","time":{"start":1744397270032,"stop":1744397270142,"duration":110}}]},"c7ae6e7ac86795ed2d12a24652cd97fd:248192c3fa65ed0ee6d08e6eb022c44f":{"statistic":{"failed":0,"broken":0,"skipped":0,"passed":1,"unknown":0,"total":1},"items":[{"uid":"767d84acb799b968","reportUrl":"https://assurdly.github.io/northquest-automation-tests/86/67//#testresult/767d84acb799b968","status":"passed","time":{"start":1744397284749,"stop":1744397285003,"duration":254}}]},"ee15fef1cfdb6f373f7618b89773e2c6:2055c9f6b7f1dd1b928109d9524f6038":{"statistic":{"failed":0,"broken":0,"skipped":0,"passed":1,"unknown":0,"total":1},"items":[{"uid":"84abbcd75926d7de","reportUrl":"https://assurdly.github.io/northquest-automation-tests/86/67//#testresult/84abbcd75926d7de","status":"passed","time":{"start":1744397267654,"stop":1744397267889,"duration":235}}]},"5a25517b2979d5d31b727fd66fb451fd:3a775664460771718bc1b888bc81c838":{"statistic":{"failed":1,"broken":0,"skipped":0,"passed":0,"unknown":0,"total":1},"items":[{"uid":"8853d68fec551b33","reportUrl":"https://assurdly.github.io/northquest-automation-tests/86/67//#testresult/8853d68fec551b33","status":"failed","statusDetails":"Status code is 200 or 202, Valid status in response","time":{"start":1744397273437,"stop":1744397273534,"duration":97}}]},"7c5f770f54239aeab791fe7508013ec7:35caa46925a79201f0dec0b86ace2541":{"statistic":{"failed":1,"broken":0,"skipped":0,"passed":0,"unknown":0,"total":1},"items":[{"uid":"6bb649e82f5f187f","reportUrl":"https://assurdly.github.io/northquest-automation-tests/86/67//#testresult/6bb649e82f5f187f","status":"failed","statusDetails":"Status code is 200, Test for valid status, Test for valid error message","time":{"start":1744397270536,"stop":1744397270634,"duration":98}}]},"e91fdb50aa142423ac0aee8848050dfb:71932cb08d3f467c3a4f7c065cdae20e":{"statistic":{"failed":0,"broken":0,"skipped":0,"passed":1,"unknown":0,"total":1},"items":[{"uid":"fb3e83a4a27d5050","reportUrl":"https://assurdly.github.io/northquest-automation-tests/86/67//#testresult/fb3e83a4a27d5050","status":"passed","time":{"start":1744397262965,"stop":1744397263042,"duration":77}}]},"c6fb69894362bb787c8609a489c1027f:aaaa6849f8b4a89623df0a519629beb7":{"statistic":{"failed":1,"broken":0,"skipped":0,"passed":0,"unknown":0,"total":1},"items":[{"uid":"3be25e64c42d1d89","reportUrl":"https://assurdly.github.io/northquest-automation-tests/86/67//#testresult/3be25e64c42d1d89","status":"failed","statusDetails":"Status code is 200 or 202, Valid status in response","time":{"start":1744397273337,"stop":1744397273435,"duration":98}}]},"289eb9f9895c14da552dce9545f0d9f8:8d1bd829c4b965a7b7f486b996d80667":{"statistic":{"failed":0,"broken":0,"skipped":0,"passed":1,"unknown":0,"total":1},"items":[{"uid":"9a003c0d8b98251d","reportUrl":"https://assurdly.github.io/northquest-automation-tests/86/67//#testresult/9a003c0d8b98251d","status":"passed","time":{"start":1744397278934,"stop":1744397279021,"duration":87}}]},"6ecb2526f1c32e343d00d6822811a8ab:d6348128107009db1ca4700d9bc54972":{"statistic":{"failed":0,"broken":0,"skipped":0,"passed":1,"unknown":0,"total":1},"items":[{"uid":"93ac01bfb906bd83","reportUrl":"https://assurdly.github.io/northquest-automation-tests/86/67//#testresult/93ac01bfb906bd83","status":"passed","time":{"start":1744397276338,"stop":1744397276448,"duration":110}}]},"777a08667229fbdcec5ab87af988e998:faf7d2986d8564fee50a481fe66b9e54":{"statistic":{"failed":0,"broken":0,"skipped":0,"passed":1,"unknown":0,"total":1},"items":[{"uid":"68f3e48d84e74747","reportUrl":"https://assurdly.github.io/northquest-automation-tests/86/67//#testresult/68f3e48d84e74747","status":"passed","time":{"start":1744397281450,"stop":1744397281565,"duration":115}}]},"0b2afd1cd9ea431e84e255e49b33f427:34ea1dceacdd7a6e082fb90fcec7626c":{"statistic":{"failed":0,"broken":0,"skipped":0,"passed":1,"unknown":0,"total":1},"items":[{"uid":"d490b6a9ae9451d2","reportUrl":"https://assurdly.github.io/northquest-automation-tests/86/67//#testresult/d490b6a9ae9451d2","status":"passed","time":{"start":1744397265412,"stop":1744397265485,"duration":73}}]},"7870e1b292cc22905e99f647c9eb55dc:4d8ba03d422f27c311a0e366ac08482e":{"statistic":{"failed":1,"broken":0,"skipped":0,"passed":0,"unknown":0,"total":1},"items":[{"uid":"6ba5e3d772d9c3a0","reportUrl":"https://assurdly.github.io/northquest-automation-tests/86/67//#testresult/6ba5e3d772d9c3a0","status":"failed","statusDetails":"Status code is 200, Test for valid status","time":{"start":1744397266632,"stop":1744397266711,"duration":79}}]},"711dd1705ff7c065a066a1b749b6d877:d5933e444b3685e4daf4fc66f7027aea":{"statistic":{"failed":1,"broken":0,"skipped":0,"passed":0,"unknown":0,"total":1},"items":[{"uid":"e794e00cb3bf757d","reportUrl":"https://assurdly.github.io/northquest-automation-tests/86/67//#testresult/e794e00cb3bf757d","status":"failed","statusDetails":"Status code is 200","time":{"start":1744397271234,"stop":1744397271342,"duration":108}}]},"60cb2cc5f0ebf90a37d811c547eb3f6c:c5d7c9d19ec6179296c02291cc7143e9":{"statistic":{"failed":0,"broken":0,"skipped":0,"passed":1,"unknown":0,"total":1},"items":[{"uid":"b93387e1f5856cd8","reportUrl":"https://assurdly.github.io/northquest-automation-tests/86/67//#testresult/b93387e1f5856cd8","status":"passed","time":{"start":1744397267087,"stop":1744397267163,"duration":76}}]},"c26ab8350bf91cb9cd0fc30907f2d718:a7bb6214972cd2423e7542342fde0b43":{"statistic":{"failed":0,"broken":0,"skipped":0,"passed":1,"unknown":0,"total":1},"items":[{"uid":"e584ef8a38e64f3c","reportUrl":"https://assurdly.github.io/northquest-automation-tests/86/67//#testresult/e584ef8a38e64f3c","status":"passed","time":{"start":1744397265255,"stop":1744397265332,"duration":77}}]},"a2ef5625e8ac68053c6f4f2a02ecb54f:248192c3fa65ed0ee6d08e6eb022c44f":{"statistic":{"failed":0,"broken":0,"skipped":0,"passed":1,"unknown":0,"total":1},"items":[{"uid":"4647837f2c6464e8","reportUrl":"https://assurdly.github.io/northquest-automation-tests/86/67//#testresult/4647837f2c6464e8","status":"passed","time":{"start":1744397284044,"stop":1744397284341,"duration":297}}]},"beef019d884fdc248bf17a78a1c9b9a8:fe867480c21e51780f490128ab0391d7":{"statistic":{"failed":0,"broken":0,"skipped":0,"passed":1,"unknown":0,"total":1},"items":[{"uid":"36ecf7d0aa753d7b","reportUrl":"https://assurdly.github.io/northquest-automation-tests/86/67//#testresult/36ecf7d0aa753d7b","status":"passed","time":{"start":1744397260117,"stop":1744397260207,"duration":90}}]},"3e892ad27519f4462a91c3b871d88396:d6348128107009db1ca4700d9bc54972":{"statistic":{"failed":0,"broken":0,"skipped":0,"passed":1,"unknown":0,"total":1},"items":[{"uid":"7189aa8f7ff356dd","reportUrl":"https://assurdly.github.io/northquest-automation-tests/86/67//#testresult/7189aa8f7ff356dd","status":"passed","time":{"start":1744397276451,"stop":1744397276634,"duration":183}}]},"612902e91f6fe18fa6979d41c4f62971:7fab04d935ef23c3fc02b9b76942cdc3":{"statistic":{"failed":0,"broken":0,"skipped":0,"passed":1,"unknown":0,"total":1},"items":[{"uid":"365e8e04149fcfb5","reportUrl":"https://assurdly.github.io/northquest-automation-tests/86/67//#testresult/365e8e04149fcfb5","status":"passed","time":{"start":1744397264673,"stop":1744397264748,"duration":75}}]},"01485af913ca0d4ca0df3c98125b9400:680e7228ba0e48d05899f86e4e0c6ea3":{"statistic":{"failed":0,"broken":0,"skipped":0,"passed":1,"unknown":0,"total":1},"items":[{"uid":"2f0c057a29a7950b","reportUrl":"https://assurdly.github.io/northquest-automation-tests/86/67//#testresult/2f0c057a29a7950b","status":"passed","time":{"start":1744397279535,"stop":1744397279657,"duration":122}}]},"a93a664ecd4967d2d990df9c6913fbad:9e1762dc583eb26c76a30deef69419b0":{"statistic":{"failed":0,"broken":0,"skipped":0,"passed":1,"unknown":0,"total":1},"items":[{"uid":"937c5f37aab9019f","reportUrl":"https://assurdly.github.io/northquest-automation-tests/86/67//#testresult/937c5f37aab9019f","status":"passed","time":{"start":1744397269344,"stop":1744397269419,"duration":75}}]},"0ac4056bb57e26f18588340586e06bae:bfbdaf9c62af851f0d5e7b3fc52e81a4":{"statistic":{"failed":1,"broken":0,"skipped":0,"passed":0,"unknown":0,"total":1},"items":[{"uid":"c4a35d6a930c8f0e","reportUrl":"https://assurdly.github.io/northquest-automation-tests/86/67//#testresult/c4a35d6a930c8f0e","status":"failed","statusDetails":"Status code is 400","time":{"start":1744397275831,"stop":1744397275931,"duration":100}}]},"1fa287913f4ee2a41bcf8562a5530388:ed047fff08a115377e51bfed4efa33ea":{"statistic":{"failed":0,"broken":0,"skipped":0,"passed":1,"unknown":0,"total":1},"items":[{"uid":"b7db81bc87ede080","reportUrl":"https://assurdly.github.io/northquest-automation-tests/86/67//#testresult/b7db81bc87ede080","status":"passed","time":{"start":1744397282829,"stop":1744397282905,"duration":76}}]},"996979431ad7cef9f5bb4ad025e0cbc8:5079032bf07ff79105b4fef8ec176fed":{"statistic":{"failed":0,"broken":0,"skipped":0,"passed":1,"unknown":0,"total":1},"items":[{"uid":"110461c80fbd60f2","reportUrl":"https://assurdly.github.io/northquest-automation-tests/86/67//#testresult/110461c80fbd60f2","status":"passed","time":{"start":1744397268244,"stop":1744397268337,"duration":93}}]},"fbd44a75cd01b2448c585b59aee8a7fe:b9855ea962379312cb2697ea7cc793e7":{"statistic":{"failed":0,"broken":0,"skipped":0,"passed":1,"unknown":0,"total":1},"items":[{"uid":"116a36d9694931","reportUrl":"https://assurdly.github.io/northquest-automation-tests/86/67//#testresult/116a36d9694931","status":"passed","time":{"start":1744397264505,"stop":1744397264593,"duration":88}}]},"632a143d106b133ff4a8664c32da6f05:efccc2aa2be85b86f39fd9974b37af0e":{"statistic":{"failed":1,"broken":0,"skipped":0,"passed":0,"unknown":0,"total":1},"items":[{"uid":"5d246249839e0205","reportUrl":"https://assurdly.github.io/northquest-automation-tests/86/67//#testresult/5d246249839e0205","status":"failed","statusDetails":"Status code is 200 or 202, Valid status in response","time":{"start":1744397273651,"stop":1744397273736,"duration":85}}]},"852ff1851183fa8047368d682fa396a4:fe867480c21e51780f490128ab0391d7":{"statistic":{"failed":0,"broken":0,"skipped":0,"passed":1,"unknown":0,"total":1},"items":[{"uid":"3a1e87b63e63fd3e","reportUrl":"https://assurdly.github.io/northquest-automation-tests/86/67//#testresult/3a1e87b63e63fd3e","status":"passed","time":{"start":1744397260017,"stop":1744397260114,"duration":97}}]},"63f87b6d864c447e8860143cbeba844d:5e731fec419d993dd0245aebe172d292":{"statistic":{"failed":1,"broken":0,"skipped":0,"passed":0,"unknown":0,"total":1},"items":[{"uid":"57dca0c5f5e17403","reportUrl":"https://assurdly.github.io/northquest-automation-tests/86/67//#testresult/57dca0c5f5e17403","status":"failed","statusDetails":"Successful POST request, Test for valid error message","time":{"start":1744397262397,"stop":1744397262474,"duration":77}}]},"6a6a378cccd6045558b2ea6eca75974b:59e098cf1f0ea3e6371b513f1c3b1436":{"statistic":{"failed":1,"broken":0,"skipped":0,"passed":0,"unknown":0,"total":1},"items":[{"uid":"26aa6162ad37883e","reportUrl":"https://assurdly.github.io/northquest-automation-tests/86/67//#testresult/26aa6162ad37883e","status":"failed","statusDetails":"Status code is 200 or 202, Valid status in response","time":{"start":1744397275434,"stop":1744397275534,"duration":100}}]},"04d8eb188bbc897f2e8b5d4cbb09a54f:54b1ebeff1195ccd8867cdb77aba8c6d":{"statistic":{"failed":0,"broken":0,"skipped":0,"passed":1,"unknown":0,"total":1},"items":[{"uid":"1041169a8c05c27c","reportUrl":"https://assurdly.github.io/northquest-automation-tests/86/67//#testresult/1041169a8c05c27c","status":"passed","time":{"start":1744397282312,"stop":1744397282387,"duration":75}}]},"52452e3db081301d3e9753f5ee8b527d:c1282e0ef473eab37bbff0cf2bf7cbd6":{"statistic":{"failed":1,"broken":0,"skipped":0,"passed":0,"unknown":0,"total":1},"items":[{"uid":"70af51e69849bd84","reportUrl":"https://assurdly.github.io/northquest-automation-tests/86/67//#testresult/70af51e69849bd84","status":"failed","statusDetails":"Status code is 200 or 202, Valid status in response","time":{"start":1744397275934,"stop":1744397276034,"duration":100}}]},"92df4dc31ab0932b0e12865af3a72878:eed5bcb602406c5a4a93239bb9d3be3f":{"statistic":{"failed":1,"broken":0,"skipped":0,"passed":0,"unknown":0,"total":1},"items":[{"uid":"e90add8db406bbab","reportUrl":"https://assurdly.github.io/northquest-automation-tests/86/67//#testresult/e90add8db406bbab","status":"failed","statusDetails":"Status code is 200, Test for valid error message","time":{"start":1744397268035,"stop":1744397268137,"duration":102}}]},"89e3fff5a31b393fe9fd54b7a15dcb99:b44c70a2950de5d0f49fee080f83001b":{"statistic":{"failed":0,"broken":0,"skipped":0,"passed":1,"unknown":0,"total":1},"items":[{"uid":"466a3dc0d54266d7","reportUrl":"https://assurdly.github.io/northquest-automation-tests/86/67//#testresult/466a3dc0d54266d7","status":"passed","time":{"start":1744397266939,"stop":1744397267009,"duration":70}}]},"f80219812deef3e1c7ce281222fc2928:71932cb08d3f467c3a4f7c065cdae20e":{"statistic":{"failed":1,"broken":0,"skipped":0,"passed":0,"unknown":0,"total":1},"items":[{"uid":"7aebcde1a71b4539","reportUrl":"https://assurdly.github.io/northquest-automation-tests/86/67//#testresult/7aebcde1a71b4539","status":"failed","statusDetails":"Tests for successfull Request, Status code is 200","time":{"start":1744397263407,"stop":1744397263488,"duration":81}}]},"9b5ac88d8b4ca764ab43948527aade39:40ce0dc301198129b75da644f3ab8e93":{"statistic":{"failed":0,"broken":0,"skipped":0,"passed":1,"unknown":0,"total":1},"items":[{"uid":"b2dc78a6f6a0228","reportUrl":"https://assurdly.github.io/northquest-automation-tests/86/67//#testresult/b2dc78a6f6a0228","status":"passed","time":{"start":1744397266157,"stop":1744397266240,"duration":83}}]},"b37ac35d7ec32dc1f9c5a109052f52c1:90433897863ba77f9c9ecf49f27fd67d":{"statistic":{"failed":0,"broken":0,"skipped":0,"passed":1,"unknown":0,"total":1},"items":[{"uid":"a61b89281431707","reportUrl":"https://assurdly.github.io/northquest-automation-tests/86/67//#testresult/a61b89281431707","status":"passed","time":{"start":1744397266480,"stop":1744397266553,"duration":73}}]},"40359e4217a5e0ede028f5f66e08e979:90a02cf76229ac6aed6d8dcb0e91e0bb":{"statistic":{"failed":0,"broken":0,"skipped":0,"passed":1,"unknown":0,"total":1},"items":[{"uid":"2949923f883c29ff","reportUrl":"https://assurdly.github.io/northquest-automation-tests/86/67//#testresult/2949923f883c29ff","status":"passed","time":{"start":1744397279325,"stop":1744397279426,"duration":101}}]},"67bfc86c4bd0c2bab4eeb5cb7f25fcd6:bb2da2a0a883b0e2e5e68dd580c595f0":{"statistic":{"failed":0,"broken":0,"skipped":0,"passed":1,"unknown":0,"total":1},"items":[{"uid":"40a4ffcd417e019b","reportUrl":"https://assurdly.github.io/northquest-automation-tests/86/67//#testresult/40a4ffcd417e019b","status":"passed","time":{"start":1744397265639,"stop":1744397265747,"duration":108}}]},"ee53a3d541c167b25af6c60d7b935d09:4a8026faab7718a003f642454759a499":{"statistic":{"failed":0,"broken":0,"skipped":0,"passed":1,"unknown":0,"total":1},"items":[{"uid":"5041ae7f4915d72a","reportUrl":"https://assurdly.github.io/northquest-automation-tests/86/67//#testresult/5041ae7f4915d72a","status":"passed","time":{"start":1744397262146,"stop":1744397262221,"duration":75}}]},"930786834cec9da4b9d3ac8ff47de559:5e731fec419d993dd0245aebe172d292":{"statistic":{"failed":0,"broken":0,"skipped":0,"passed":1,"unknown":0,"total":1},"items":[{"uid":"83170a574196c18b","reportUrl":"https://assurdly.github.io/northquest-automation-tests/86/67//#testresult/83170a574196c18b","status":"passed","time":{"start":1744397262557,"stop":1744397262632,"duration":75}}]},"d293cf03135dea9f747ab5ecbabc4604:70458ddd326019ff6ad63bc9c48623f0":{"statistic":{"failed":0,"broken":0,"skipped":0,"passed":1,"unknown":0,"total":1},"items":[{"uid":"53bca412136b0385","reportUrl":"https://assurdly.github.io/northquest-automation-tests/86/67//#testresult/53bca412136b0385","status":"passed","time":{"start":1744397281680,"stop":1744397281758,"duration":78}}]},"f950f9c821d66cd4ec0f6f0b5263c37f:b8b458edaebfa8b1878f9d6cf27323e5":{"statistic":{"failed":1,"broken":0,"skipped":0,"passed":0,"unknown":0,"total":1},"items":[{"uid":"4960a3cc66018342","reportUrl":"https://assurdly.github.io/northquest-automation-tests/86/67//#testresult/4960a3cc66018342","status":"failed","statusDetails":"Status code is 400, Test for valid error message","time":{"start":1744397269644,"stop":1744397269738,"duration":94}}]},"ef69a16a5a5fa02bd0290f524a9c67b1:b1f2c02e1bc3f8612815a30fd01f4b5f":{"statistic":{"failed":0,"broken":0,"skipped":0,"passed":1,"unknown":0,"total":1},"items":[{"uid":"c86522e17bb51983","reportUrl":"https://assurdly.github.io/northquest-automation-tests/86/67//#testresult/c86522e17bb51983","status":"passed","time":{"start":1744397269140,"stop":1744397269233,"duration":93}}]},"c61af9b60be52a29efa6562ef952564a:8560e7c9c38a61919038b56dd1cc83ff":{"statistic":{"failed":1,"broken":0,"skipped":0,"passed":0,"unknown":0,"total":1},"items":[{"uid":"87dd6af3f1d790eb","reportUrl":"https://assurdly.github.io/northquest-automation-tests/86/67//#testresult/87dd6af3f1d790eb","status":"failed","statusDetails":"Status code is 400, Test for valid error message","time":{"start":1744397268456,"stop":1744397268541,"duration":85}}]},"bf80df4392aff9317150bbe7bbbe4675:4ffb31585b8d645b55f6e21043173da0":{"statistic":{"failed":1,"broken":0,"skipped":0,"passed":0,"unknown":0,"total":1},"items":[{"uid":"2b331fd9d55ab47d","reportUrl":"https://assurdly.github.io/northquest-automation-tests/86/67//#testresult/2b331fd9d55ab47d","status":"failed","statusDetails":"Status code is 200 or 202, Valid status in response","time":{"start":1744397274032,"stop":1744397274130,"duration":98}}]},"d0adc2bc034db417437771e4e73e88cb:b75ec150b1ce16070283601f53ea6564":{"statistic":{"failed":0,"broken":0,"skipped":0,"passed":1,"unknown":0,"total":1},"items":[{"uid":"5e24aaf1be47563a","reportUrl":"https://assurdly.github.io/northquest-automation-tests/86/67//#testresult/5e24aaf1be47563a","status":"passed","time":{"start":1744397264121,"stop":1744397264191,"duration":70}}]},"af3144928e5c009b3ad585ae31961ec7:4a8026faab7718a003f642454759a499":{"statistic":{"failed":0,"broken":0,"skipped":0,"passed":1,"unknown":0,"total":1},"items":[{"uid":"9f1fc34813b0b66c","reportUrl":"https://assurdly.github.io/northquest-automation-tests/86/67//#testresult/9f1fc34813b0b66c","status":"passed","time":{"start":1744397261651,"stop":1744397262061,"duration":410}}]},"3f89fe45a501886b7fb01f79f810b930:44b5f2295c4e589d690e958a6f3116f2":{"statistic":{"failed":0,"broken":0,"skipped":0,"passed":1,"unknown":0,"total":1},"items":[{"uid":"dd407891a5755a83","reportUrl":"https://assurdly.github.io/northquest-automation-tests/86/67//#testresult/dd407891a5755a83","status":"passed","time":{"start":1744397280429,"stop":1744397280725,"duration":296}}]},"812b81ff2aced99e103d6eec28a70867:a7bb6214972cd2423e7542342fde0b43":{"statistic":{"failed":0,"broken":0,"skipped":0,"passed":1,"unknown":0,"total":1},"items":[{"uid":"1ca333dfd5c908ad","reportUrl":"https://assurdly.github.io/northquest-automation-tests/86/67//#testresult/1ca333dfd5c908ad","status":"passed","time":{"start":1744397263491,"stop":1744397263567,"duration":76}}]},"daa2eba6feaf800b5dfc9ca0589f38d6:4a8026faab7718a003f642454759a499":{"statistic":{"failed":0,"broken":0,"skipped":0,"passed":1,"unknown":0,"total":1},"items":[{"uid":"78414309d3c8a729","reportUrl":"https://assurdly.github.io/northquest-automation-tests/86/67//#testresult/78414309d3c8a729","status":"passed","time":{"start":1744397262064,"stop":1744397262143,"duration":79}}]},"4af304e14f1be2023407cdcdb874da10:fe867480c21e51780f490128ab0391d7":{"statistic":{"failed":0,"broken":0,"skipped":0,"passed":1,"unknown":0,"total":1},"items":[{"uid":"15058954df7c8380","reportUrl":"https://assurdly.github.io/northquest-automation-tests/86/67//#testresult/15058954df7c8380","status":"passed","time":{"start":1744397260211,"stop":1744397260321,"duration":110}}]},"67936015a38a6c37677d82c8b0b260a7:bb2da2a0a883b0e2e5e68dd580c595f0":{"statistic":{"failed":0,"broken":0,"skipped":0,"passed":1,"unknown":0,"total":1},"items":[{"uid":"453d2b045dceb988","reportUrl":"https://assurdly.github.io/northquest-automation-tests/86/67//#testresult/453d2b045dceb988","status":"passed","time":{"start":1744397282136,"stop":1744397282229,"duration":93}}]},"eea2758675c47bce97f4dc1595d26b11:e615259c5fd5b96e075b8a53b0c94b2e":{"statistic":{"failed":1,"broken":0,"skipped":0,"passed":0,"unknown":0,"total":1},"items":[{"uid":"ef7a7e074ed17d2b","reportUrl":"https://assurdly.github.io/northquest-automation-tests/86/67//#testresult/ef7a7e074ed17d2b","status":"failed","statusDetails":"Status code is 400","time":{"start":1744397275634,"stop":1744397275729,"duration":95}}]},"a30cfe475f18bb221ab646a5a806c119:4a8026faab7718a003f642454759a499":{"statistic":{"failed":0,"broken":0,"skipped":0,"passed":1,"unknown":0,"total":1},"items":[{"uid":"3c77022974b28053","reportUrl":"https://assurdly.github.io/northquest-automation-tests/86/67//#testresult/3c77022974b28053","status":"passed","time":{"start":1744397262224,"stop":1744397262299,"duration":75}}]},"f153bc8d21cc5a1c29badd455ac88e15:71932cb08d3f467c3a4f7c065cdae20e":{"statistic":{"failed":0,"broken":0,"skipped":0,"passed":1,"unknown":0,"total":1},"items":[{"uid":"2008580837f58069","reportUrl":"https://assurdly.github.io/northquest-automation-tests/86/67//#testresult/2008580837f58069","status":"passed","time":{"start":1744397262803,"stop":1744397262883,"duration":80}}]},"0250bebba97ff87b66808eef2b03add5:4a0f654ab80e39689a4fa33a9a6474bb":{"statistic":{"failed":1,"broken":0,"skipped":0,"passed":0,"unknown":0,"total":1},"items":[{"uid":"26b9ed06411d8003","reportUrl":"https://assurdly.github.io/northquest-automation-tests/86/67//#testresult/26b9ed06411d8003","status":"failed","statusDetails":"Status code is 400","time":{"start":1744397272275,"stop":1744397272433,"duration":158}}]},"21af83041c9ffab6891e70b176f5aac6:6f084bd85e73ea356365cddb6d3ea28f":{"statistic":{"failed":0,"broken":0,"skipped":0,"passed":1,"unknown":0,"total":1},"items":[{"uid":"c9e83df82963f69b","reportUrl":"https://assurdly.github.io/northquest-automation-tests/86/67//#testresult/c9e83df82963f69b","status":"passed","time":{"start":1744397280331,"stop":1744397280426,"duration":95}}]},"14726bdf43382dce508a226e3db71ea0:42c481fda1050023fabe6c8f4200cc8f":{"statistic":{"failed":0,"broken":0,"skipped":0,"passed":1,"unknown":0,"total":1},"items":[{"uid":"2ffadfbd5304bc9e","reportUrl":"https://assurdly.github.io/northquest-automation-tests/86/67//#testresult/2ffadfbd5304bc9e","status":"passed","time":{"start":1744397265750,"stop":1744397265828,"duration":78}}]},"1ba72b4bb59cf646d8be596f8d4dfc58:097c24511db99c18a84d7ac97bf3f8cd":{"statistic":{"failed":0,"broken":0,"skipped":0,"passed":1,"unknown":0,"total":1},"items":[{"uid":"44a42d23eccca5a8","reportUrl":"https://assurdly.github.io/northquest-automation-tests/86/67//#testresult/44a42d23eccca5a8","status":"passed","time":{"start":1744397282231,"stop":1744397282309,"duration":78}}]},"d629813381b209990fadd4769101e449:2af82c6093fb06de4b33dfe060f1ec67":{"statistic":{"failed":1,"broken":0,"skipped":0,"passed":0,"unknown":0,"total":1},"items":[{"uid":"f072969d9e7315ad","reportUrl":"https://assurdly.github.io/northquest-automation-tests/86/67//#testresult/f072969d9e7315ad","status":"failed","statusDetails":"Status code is 400","time":{"start":1744397265921,"stop":1744397266002,"duration":81}}]},"9a899b4c2af54aa35db7a6338d69c6df:9eb119d7374cc645f793b1fecc1d7d5d":{"statistic":{"failed":0,"broken":0,"skipped":0,"passed":1,"unknown":0,"total":1},"items":[{"uid":"eee897dd9564e65","reportUrl":"https://assurdly.github.io/northquest-automation-tests/86/67//#testresult/eee897dd9564e65","status":"passed","time":{"start":1744397284343,"stop":1744397284554,"duration":211}}]},"69d5e5a3124b17917f4889828fe77814:022af40f8bae7ac6be9f5cbb3d498c77":{"statistic":{"failed":0,"broken":0,"skipped":0,"passed":1,"unknown":0,"total":1},"items":[{"uid":"5a2b0ccb1e5ab976","reportUrl":"https://assurdly.github.io/northquest-automation-tests/86/67//#testresult/5a2b0ccb1e5ab976","status":"passed","time":{"start":1744397263808,"stop":1744397263889,"duration":81}}]},"7c5ffd7b537b5d397c879b28f1effefd:e666844f157d0e89746dc4662c984d6d":{"statistic":{"failed":0,"broken":0,"skipped":0,"passed":1,"unknown":0,"total":1},"items":[{"uid":"30c5a459275c7532","reportUrl":"https://assurdly.github.io/northquest-automation-tests/86/67//#testresult/30c5a459275c7532","status":"passed","time":{"start":1744397280937,"stop":1744397281040,"duration":103}}]},"ad3eeb460bacfb73614e2bc2a5c1abb1:3877a0c673699b75a6eebc1dc0471a4e":{"statistic":{"failed":1,"broken":0,"skipped":0,"passed":0,"unknown":0,"total":1},"items":[{"uid":"5995242bf2a7030e","reportUrl":"https://assurdly.github.io/northquest-automation-tests/86/67//#testresult/5995242bf2a7030e","status":"failed","statusDetails":"Status code is 400","time":{"start":1744397270936,"stop":1744397271034,"duration":98}}]},"c93848f2871efcea267eb40c5584e6f6:71932cb08d3f467c3a4f7c065cdae20e":{"statistic":{"failed":0,"broken":0,"skipped":0,"passed":1,"unknown":0,"total":1},"items":[{"uid":"2de733d8bff9088","reportUrl":"https://assurdly.github.io/northquest-automation-tests/86/67//#testresult/2de733d8bff9088","status":"passed","time":{"start":1744397262885,"stop":1744397262963,"duration":78}}]},"c496695b74aaed25bd5294dac609f9a2:e615259c5fd5b96e075b8a53b0c94b2e":{"statistic":{"failed":1,"broken":0,"skipped":0,"passed":0,"unknown":0,"total":1},"items":[{"uid":"bfa8dd00a4ee3821","reportUrl":"https://assurdly.github.io/northquest-automation-tests/86/67//#testresult/bfa8dd00a4ee3821","status":"failed","statusDetails":"Status code is 400","time":{"start":1744397275131,"stop":1744397275205,"duration":74}}]},"21d1debec10d3bb6ce3e80a4e0a1ca00:90433897863ba77f9c9ecf49f27fd67d":{"statistic":{"failed":1,"broken":0,"skipped":0,"passed":0,"unknown":0,"total":1},"items":[{"uid":"46ebee617e945535","reportUrl":"https://assurdly.github.io/northquest-automation-tests/86/67//#testresult/46ebee617e945535","status":"failed","statusDetails":"Status code is 200, Test for valid status, Test for valid error message","time":{"start":1744397266243,"stop":1744397266323,"duration":80}}]},"26ab05d3f37d497233c5c449085910aa:91a15240af237f6424626a459f3b98cf":{"statistic":{"failed":1,"broken":0,"skipped":0,"passed":0,"unknown":0,"total":1},"items":[{"uid":"afabacf08f09277e","reportUrl":"https://assurdly.github.io/northquest-automation-tests/86/67//#testresult/afabacf08f09277e","status":"failed","statusDetails":"Status code is 400","time":{"start":1744397275335,"stop":1744397275431,"duration":96}}]},"bc1a83e00ee207d84cf546da5b8d5489:3f52e95c18d06b7bc1317842af109246":{"statistic":{"failed":0,"broken":0,"skipped":0,"passed":1,"unknown":0,"total":1},"items":[{"uid":"9033bc275df6f600","reportUrl":"https://assurdly.github.io/northquest-automation-tests/86/67//#testresult/9033bc275df6f600","status":"passed","time":{"start":1744397267334,"stop":1744397267433,"duration":99}}]},"d1a9e2e8763584f03d0d52e5c96b992b:43bd7fa8891b19b5169f0c8dd44b26bc":{"statistic":{"failed":0,"broken":0,"skipped":0,"passed":1,"unknown":0,"total":1},"items":[{"uid":"e8a946e7f8f92bb4","reportUrl":"https://assurdly.github.io/northquest-automation-tests/86/67//#testresult/e8a946e7f8f92bb4","status":"passed","time":{"start":1744397272642,"stop":1744397272713,"duration":71}}]},"b47593695fa10ae0df00c3539993d1a0:c382cc4b40b1c85914b603afaf8780f6":{"statistic":{"failed":0,"broken":0,"skipped":0,"passed":1,"unknown":0,"total":1},"items":[{"uid":"f7152bdaf89c5bc3","reportUrl":"https://assurdly.github.io/northquest-automation-tests/86/67//#testresult/f7152bdaf89c5bc3","status":"passed","time":{"start":1744397264425,"stop":1744397264503,"duration":78}}]},"27bddcaa7cbe8b6c3b819c4c0519b46c:d854fcf8e44ec9bd1d713114badb38ea":{"statistic":{"failed":0,"broken":0,"skipped":0,"passed":1,"unknown":0,"total":1},"items":[{"uid":"f3fd9e0d1e1b450c","reportUrl":"https://assurdly.github.io/northquest-automation-tests/86/67//#testresult/f3fd9e0d1e1b450c","status":"passed","time":{"start":1744397282533,"stop":1744397282626,"duration":93}}]},"ffbeb1afc0c1f290e53127f938cfdf50:ed2c2779c911c821b58b03549973316a":{"statistic":{"failed":1,"broken":0,"skipped":0,"passed":0,"unknown":0,"total":1},"items":[{"uid":"f3a201c89f88f544","reportUrl":"https://assurdly.github.io/northquest-automation-tests/86/67//#testresult/f3a201c89f88f544","status":"failed","statusDetails":"Status code is 200 or 202, Valid status in response","time":{"start":1744397274338,"stop":1744397274439,"duration":101}}]},"f7fbd4bc5b94eca685bbe91ca577c81d:a7bb6214972cd2423e7542342fde0b43":{"statistic":{"failed":1,"broken":0,"skipped":0,"passed":0,"unknown":0,"total":1},"items":[{"uid":"9920100ddaf68afa","reportUrl":"https://assurdly.github.io/northquest-automation-tests/86/67//#testresult/9920100ddaf68afa","status":"failed","statusDetails":"Tests for Invalid old password, Status code is 400","time":{"start":1744397265099,"stop":1744397265174,"duration":75}}]},"d8203541fe2a464b234659ea0a39f4f9:c5d7c9d19ec6179296c02291cc7143e9":{"statistic":{"failed":0,"broken":0,"skipped":0,"passed":1,"unknown":0,"total":1},"items":[{"uid":"ff37c3b28049948f","reportUrl":"https://assurdly.github.io/northquest-automation-tests/86/67//#testresult/ff37c3b28049948f","status":"passed","time":{"start":1744397267011,"stop":1744397267084,"duration":73}}]},"e09c4aec5a5334c8a13d74accff721d2:9e551985ab4c93f6dabc73a2c03e5ad2":{"statistic":{"failed":0,"broken":0,"skipped":0,"passed":1,"unknown":0,"total":1},"items":[{"uid":"f92a7d86302fe031","reportUrl":"https://assurdly.github.io/northquest-automation-tests/86/67//#testresult/f92a7d86302fe031","status":"passed","time":{"start":1744397266004,"stop":1744397266078,"duration":74}}]},"cf54d7895a024b5b0bc2a1c6a65ee192:f92507a6bd40de44fdeebcf5e2adf551":{"statistic":{"failed":0,"broken":0,"skipped":0,"passed":1,"unknown":0,"total":1},"items":[{"uid":"e58af2651888cce6","reportUrl":"https://assurdly.github.io/northquest-automation-tests/86/67//#testresult/e58af2651888cce6","status":"passed","time":{"start":1744397260616,"stop":1744397260694,"duration":78}}]},"8f0fda22d3fa2b42945e8cbabe6b708d:f92507a6bd40de44fdeebcf5e2adf551":{"statistic":{"failed":0,"broken":0,"skipped":0,"passed":1,"unknown":0,"total":1},"items":[{"uid":"c9aaa6f56c6ef4a6","reportUrl":"https://assurdly.github.io/northquest-automation-tests/86/67//#testresult/c9aaa6f56c6ef4a6","status":"passed","time":{"start":1744397260440,"stop":1744397260525,"duration":85}}]},"438c378c4ad99cb7d00fdaf4b3eccc1f:aee2c59d4146ada7bd55fa7af78c731a":{"statistic":{"failed":0,"broken":0,"skipped":0,"passed":1,"unknown":0,"total":1},"items":[{"uid":"4ba804fe5e13a677","reportUrl":"https://assurdly.github.io/northquest-automation-tests/86/67//#testresult/4ba804fe5e13a677","status":"passed","time":{"start":1744397272831,"stop":1744397273127,"duration":296}}]},"dd82b7372bca7c0cffed6dc4577e7f11:70458ddd326019ff6ad63bc9c48623f0":{"statistic":{"failed":0,"broken":0,"skipped":0,"passed":1,"unknown":0,"total":1},"items":[{"uid":"646919e11c5fd67d","reportUrl":"https://assurdly.github.io/northquest-automation-tests/86/67//#testresult/646919e11c5fd67d","status":"passed","time":{"start":1744397281761,"stop":1744397281854,"duration":93}}]},"44b2d63a5aceda8a7483ecc8a00662d5:54f7b78c5ec1053bf4b4bb37b929eb43":{"statistic":{"failed":1,"broken":0,"skipped":0,"passed":0,"unknown":0,"total":1},"items":[{"uid":"ab45d64a5c630649","reportUrl":"https://assurdly.github.io/northquest-automation-tests/86/67//#testresult/ab45d64a5c630649","status":"failed","statusDetails":"Valid Error messages returned","time":{"start":1744397261364,"stop":1744397261465,"duration":101}}]},"d178cf23e40e80eb456b185414e63e56:1b68b82125563fdfd4bafaad8d9d5790":{"statistic":{"failed":1,"broken":0,"skipped":0,"passed":0,"unknown":0,"total":1},"items":[{"uid":"8793057012e0d0fb","reportUrl":"https://assurdly.github.io/northquest-automation-tests/86/67//#testresult/8793057012e0d0fb","status":"failed","statusDetails":"Status code is 400, Response status is \"error\" , Test for valid error message","time":{"start":1744397264270,"stop":1744397264344,"duration":74}}]},"ef278b9fc8e4eb4e5160b9887b18d758:814764c3bb7d7ee820cbc161fd7dae14":{"statistic":{"failed":0,"broken":0,"skipped":0,"passed":1,"unknown":0,"total":1},"items":[{"uid":"3559d154786051f2","reportUrl":"https://assurdly.github.io/northquest-automation-tests/86/67//#testresult/3559d154786051f2","status":"passed","time":{"start":1744397267165,"stop":1744397267237,"duration":72}}]},"9736527083537c05c77b53ba5860376a:9acda0a901b8cd32cd0c491245e0782c":{"statistic":{"failed":1,"broken":0,"skipped":0,"passed":0,"unknown":0,"total":1},"items":[{"uid":"9cb9d44af793ee75","reportUrl":"https://assurdly.github.io/northquest-automation-tests/86/67//#testresult/9cb9d44af793ee75","status":"failed","statusDetails":"Status code is 400","time":{"start":1744397274442,"stop":1744397274529,"duration":87}}]},"f7614e7cef06a43b0c7e6629a03d2793:3f60efe49de4c4058f31170a66e03017":{"statistic":{"failed":0,"broken":0,"skipped":0,"passed":1,"unknown":0,"total":1},"items":[{"uid":"f2e76306eead36bc","reportUrl":"https://assurdly.github.io/northquest-automation-tests/86/67//#testresult/f2e76306eead36bc","status":"passed","time":{"start":1744397283637,"stop":1744397283704,"duration":67}}]},"d578692f3fba4b340354423b88f59d00:a0bfa8d4c548b1464afcd5d89227c578":{"statistic":{"failed":1,"broken":0,"skipped":0,"passed":0,"unknown":0,"total":1},"items":[{"uid":"c3c5ff1968344cf","reportUrl":"https://assurdly.github.io/northquest-automation-tests/86/67//#testresult/c3c5ff1968344cf","status":"failed","statusDetails":"Status code is 400","time":{"start":1744397273840,"stop":1744397273932,"duration":92}}]},"34c92c32c11824ec266c7938321ecc20:dbd5151222b3664d3ad8e9df01768700":{"statistic":{"failed":1,"broken":0,"skipped":0,"passed":0,"unknown":0,"total":1},"items":[{"uid":"7f570f1f3d31a24d","reportUrl":"https://assurdly.github.io/northquest-automation-tests/86/67//#testresult/7f570f1f3d31a24d","status":"failed","statusDetails":"Status code is 200","time":{"start":1744397270834,"stop":1744397270933,"duration":99}}]},"870fcd0d8fbf814409fd997f99c8b193:71932cb08d3f467c3a4f7c065cdae20e":{"statistic":{"failed":1,"broken":0,"skipped":0,"passed":0,"unknown":0,"total":1},"items":[{"uid":"3ff10a1f7ff89d3f","reportUrl":"https://assurdly.github.io/northquest-automation-tests/86/67//#testresult/3ff10a1f7ff89d3f","status":"failed","statusDetails":"Tests for successfull Request, Status code is 200","time":{"start":1744397262720,"stop":1744397262800,"duration":80}}]},"687635b915c0fb00a9408191351145f9:4a886b1429fb813085997dbefc55929c":{"statistic":{"failed":1,"broken":0,"skipped":0,"passed":0,"unknown":0,"total":1},"items":[{"uid":"f3ee129024d3ea30","reportUrl":"https://assurdly.github.io/northquest-automation-tests/86/67//#testresult/f3ee129024d3ea30","status":"failed","statusDetails":"Status code is 404, Test for valid error message","time":{"start":1744397277836,"stop":1744397277955,"duration":119}}]},"504a10806b30d80a0e31b10f58d349f0:6fbfa581fb82b49b3a6f9636f98089fd":{"statistic":{"failed":1,"broken":0,"skipped":0,"passed":0,"unknown":0,"total":1},"items":[{"uid":"eb7dec56bd5ccb81","reportUrl":"https://assurdly.github.io/northquest-automation-tests/86/67//#testresult/eb7dec56bd5ccb81","status":"failed","statusDetails":"Status code is 200 or 202, Valid status in response","time":{"start":1744397274235,"stop":1744397274335,"duration":100}}]},"793494eb5812bedc21495ff59cfad655:2443eae92279571f623c7a6a1e438709":{"statistic":{"failed":0,"broken":0,"skipped":0,"passed":1,"unknown":0,"total":1},"items":[{"uid":"6d0ba066387f2b26","reportUrl":"https://assurdly.github.io/northquest-automation-tests/86/67//#testresult/6d0ba066387f2b26","status":"passed","time":{"start":1744397264751,"stop":1744397264824,"duration":73}}]},"1048daddc44f04c7fd06cead7b49b6b6:c4f80cc68d1c0d13c250b2945fdaad67":{"statistic":{"failed":1,"broken":0,"skipped":0,"passed":0,"unknown":0,"total":1},"items":[{"uid":"c7f2c7bdbc160834","reportUrl":"https://assurdly.github.io/northquest-automation-tests/86/67//#testresult/c7f2c7bdbc160834","status":"failed","statusDetails":"Status code is 200","time":{"start":1744397277232,"stop":1744397277435,"duration":203}}]},"1e544f253c8fed1898bd7a4c4cc30b60:5017b06d3643254b82d3706a3d5d5ec5":{"statistic":{"failed":1,"broken":0,"skipped":0,"passed":0,"unknown":0,"total":1},"items":[{"uid":"2e1a0dc941cbf6bf","reportUrl":"https://assurdly.github.io/northquest-automation-tests/86/67//#testresult/2e1a0dc941cbf6bf","status":"failed","statusDetails":"Status code is 200 or 202, Valid status in response","time":{"start":1744397273226,"stop":1744397273334,"duration":108}}]},"08c9ceecbe40a63066f81bdd496a74d1:990d0670189098ed720e6600f19f3a53":{"statistic":{"failed":1,"broken":0,"skipped":0,"passed":0,"unknown":0,"total":1},"items":[{"uid":"eb2d53ee049064ee","reportUrl":"https://assurdly.github.io/northquest-automation-tests/86/67//#testresult/eb2d53ee049064ee","status":"failed","statusDetails":"Test for valid error message","time":{"start":1744397279833,"stop":1744397279930,"duration":97}}]},"e6802de9794d2ad59d028ddbd556cfe9:8837d5e124aa2f36b9efe3d59c8e5a2a":{"statistic":{"failed":1,"broken":0,"skipped":0,"passed":0,"unknown":0,"total":1},"items":[{"uid":"203f8e08c013c94c","reportUrl":"https://assurdly.github.io/northquest-automation-tests/86/67//#testresult/203f8e08c013c94c","status":"failed","statusDetails":"Status code is 400, Test for valid error message","time":{"start":1744397277957,"stop":1744397278039,"duration":82}}]},"b0fa1c30a03afca5f20c4c811b13cec7:54f7b78c5ec1053bf4b4bb37b929eb43":{"statistic":{"failed":0,"broken":0,"skipped":0,"passed":1,"unknown":0,"total":1},"items":[{"uid":"6e7f4880a05acf08","reportUrl":"https://assurdly.github.io/northquest-automation-tests/86/67//#testresult/6e7f4880a05acf08","status":"passed","time":{"start":1744397261244,"stop":1744397261361,"duration":117}}]},"08431905472305a229a32251a00b313d:9acda0a901b8cd32cd0c491245e0782c":{"statistic":{"failed":1,"broken":0,"skipped":0,"passed":0,"unknown":0,"total":1},"items":[{"uid":"eed7e325cfd464eb","reportUrl":"https://assurdly.github.io/northquest-automation-tests/86/67//#testresult/eed7e325cfd464eb","status":"failed","statusDetails":"Status code is 400","time":{"start":1744397275537,"stop":1744397275632,"duration":95}}]}}